Workbook

Sheet 00_Surum_Gecmisi
A1: Sürüm Geçmişi
A2: Her geliştirme yeni sürüm olarak buraya işlenir. Güncel sürüm: v5 (2026-10-06).
A4: Sürüm | B4: Tarih | C4: Ne değişti | D4: Neden
A5: v1 | B5: 2026-10-02 | C5: İlk üretim. Dokümanın kendi isimlendirmesi (snake_case, uuid, numeric(20,6)) birebir Excel'e aktarıldı. 19 tablo + ilişki sheet'i. | D5: Dokümanın veri modelini görünür kılmak
A6: v2 | B6: 2026-10-02 | C6: Tüm tablo/kolon adları ve tipler NetTrexMM + NetTrex.OptionsFX konvansiyonuna çevrildi: Def/Txn prefix, PascalCase, uuid→int/bigint, numeric(20,6)→decimal(38,10), timestamptz→datetime, jsonb→nvarchar(MAX). SettlementType/PaymentInstructionType MM'de var olan tablolara FK'ye çevrildi. | D6: Kullanıcı dokümanın Postgres tarzı isimlendirmesini kullanmak istemedi; ev konvansiyonu esas alındı
A7: v3 | B7: 2026-10-02 | C7: Self-review bulgularının tamamı kapatıldı + DDL/repository üretimine hazır hale getirildi: • TÜM PK'ler bigint (ofis kuralı) • Her tablo için Id üretim stratejisi netleşti (DefNumberGen vs IDENTITY) • Constraint/Index sheet'i eklendi (PK_/UQ_/IX_/DF_ adlarıyla) • DB Nesneleri sheet'i eklendi (History+Trigger, DefNumberGen, FlowSet/FlowTransition, DefCountMonitoring+SP, FrameworkParameter, Menü) • Sabitler/Enum sheet'i eklendi (StateId bitmask, ActionId, tüm kod listeleri) • Tip Kuralları sheet'i eklendi • Tablo sheet'lerine Default / Index-Constraint / FK Hedefi kolonları eklendi • FlowEntity/MakerCheckerEntity audit blokları gerçek emsalden (TxnTawarruq) eklendi • Eşzamanlılık: TxnCollateralPosition opsiyonel değil ZORUNLU oldu | D7: Kullanıcı review istedi; 3 ciddi açık (Id üretimi, constraint listesi eksikliği, eşzamanlılık) + ofis tip kuralları (long Id, float/double yasak) ve SP/constraint/fonksiyon araştırması
A8: v4 | B8: 2026-10-04 | C8: 🔴 v3'ÜN BİR KARARI ÇÜRÜTÜLDÜ + fazla kolonlar temizlendi + referans kopyaları eklendi: 1) DefCollateralAnnex / DefCollateral Id'si → DefNumberGen YERİNE bigint IDENTITY. v3'te PrdProductDefinition'ı emsal almıştım; ölçüm o sayacın ÖLÜ olduğunu gösterdi (LastNumber 999 ama gerçek Id'ler 1..11; Create handler'da sayaç çağrıları yoruma alınmış). Sayaç deseni 2024-02'den sonra terk edilmiş; en yeni emsal AmortizationConfiguration (2026-04) bigint IDENTITY. DefNumberGen artık YALNIZ TxnCollateral için. 2) FlowEntity'nin 12. alanı PreviousActionId eklendi (koddan okundu; TxnTawarruq creation script'inde yoktu — script tek kaynak değil, base class asıl kaynak). 3) MakerCheckerEntity'nin CreatedBy/CreatedDate TANIMLAMADIĞI uyarısı eklendi (koddan: yalnız StateId/StateMaker/StateDate var). 4) YENİ SHEET 00_Referans_Kopyalari — her modül DB'si referans verisinin kendi kopyasını tutuyor (Common-MM kesişimi 44 tablo, Kafka ile beslenir). Collateral minimum +12 tablo / 13 topic / 12 handler → toplam 20 değil 32 tablo. 5) FAZLA KOLONLAR KALDIRILDI: 6 alt tabloda ValidFrom/ValidTo (parent revizyonu zaten geçerlilik penceresini taşıyor) · PaymentInstruction.ActiveFlow (TransactionType ile birebir tekrar) · TxnCollateral.BusinessKey (gerekçesizdi; Fimple/muhasebe faz-1 dışı). 6) Status (DRAFT/ACTIVE/INACTIVE) → IsEnabled bit. DRAFT≈StateId 16, ACTIVE≈StateId 18 olduğu için %70 tekrardı; INACTIVE'i MM'in standart IsEnabled deseni karşılıyor. | D8: Kullanıcı "gerçekten emin misin" diye sordu → 3 konu ölçümle kapatıldı. Ayrıca "AnnexProductScope'ta ValidFrom/ValidTo gerçekten gerekli mi" sorusu, dokümanın iki rakip versiyonlama desenini (immutable revizyon + effective-dated satır) üst üste taşıdığını ortaya çıkardı
A9: v5 | B9: 46301 | C9: Kimlik ve ilişki gösterimi tutarlılık düzeltmesi: • DefNumberGen yalnız TxnCollateral.Id için bırakıldı; diğer surrogate Id kolonları IDENTITY olarak kesinleştirildi. • 20 tablo sheet’ine açık PK/FK/UQ ve FK → hedef PK eşleşme kolonu eklendi. • Composite UQ alanları UQ1/UQ2/UQ3 grup etiketiyle gösterildi. • MarginRule UQ’dan kaldırılmış ValidFrom çıkarıldı. • v4’ten kalan Status ve ID üretimi çelişkileri temizlendi. | D9: Kullanıcı, güncel IDENTITY kararının tüm sheet’lerde uygulanmasını ve UML’deki açık anahtar eşleşmelerinin tablo sheet’lerinde de görünmesini istedi.

Sheet 00_Genel_Bakis
A1: Collateral Modülü — DB Şeması (v5)
A2: Kaynak: Hazine_Teminat_Yonetimi_Fonksiyonel_Teknik_Analiz v1.4 (30.09.2026) · Konvansiyon: NetTrexMM fiziksel şeması + .ai-agent/skills/db-script.md + Örnek_Scriptler/6-NetTrexMM-Tawarruq.sql emsali · Hedef DB: NetTrexCollateral (ad kesinleşmedi)
A4: Ekranlar
A5: # | B5: Ekran | C5: Açıklama | D5: İlişkili tablolar
A6: 1 | B6: Collateral Annex | C6: Sözleşmesel çerçeve. İçinde 2 popup: Add Product, Add Rule. | D6: DefCollateralAnnex, DefCollateralAnnexProductScope, DefCollateralAnnexMarginRule
A7: 2 | B7: Collateral Definition | C7: Cash veya Security varyantlı (CollateralType paneli seçer). | D7: DefCollateral + 6 alt tablo
A8: 3 | B8: Collateral Transaction | C8: Increase/Decrease + Limit Status + Near Payment Instructions. | D8: TxnCollateral, TxnCollateralCash, TxnCollateralSecurity, TxnCollateralLimit, TxnCollateralPaymentInstruction
A9: 4 | B9: Transaction Detail | C9: Kendi tablosu YOK — ledger'dan re-derive edilen salt-okunur tarihçe/running balance. | D9: (view/projection; TxnCollateralPosition hızlandırır)
A11: Tablolar — kategori ve Id stratejisi
A12: Tablo | B12: Kategori | C12: Id üretimi | D12: History + Trigger | E12: Not
A13: DefCollateralAnnex | B13: Maker-checker tanım (ekrandan düzenlenir) | C13: bigint IDENTITY | D13: ✅ gerekli | E13: 🔑 v4 DÜZELTMESİ: v3'te DefNumberGen demiştim, YANLIŞTI. Emsal aldığım PrdProductDefinition sayacı ÖLÜ (LastNumber 999, gerçek Id 1..11, Create handler'da sayaç çağrıları yoruma alınmış). Doğru emsal: AmortizationConfiguration (2026-04, bigint IDENTITY)
A14: DefCollateralAnnexProductScope | B14: Tanım alt tablosu | C14: bigint IDENTITY | D14: ❌ (saf eşleme — parent revizyonu kapsıyor) | E14: Add Product satırları. Emsal: PrdProductDefinitionMarketMap History almıyor
A15: DefCollateralAnnexMarginRule | B15: Tanım alt tablosu | C15: bigint IDENTITY | D15: ⚠️ TARTIŞMALI — parasal şart taşıyor | E15: Add Rule satırları (Threshold/MTA/Rounding). Emsal ayrımı: parasal/iş şartı taşıyan alt kayıt History ALIR (TxnCashFlow, AmortizationConfiguration); saf eşleme ALMAZ. Revizyon deseni sıkı uygulanırsa gerekmez
A16: DefCollateral | B16: Maker-checker tanım (ekrandan düzenlenir) | C16: bigint IDENTITY | D16: ✅ gerekli | E16: 🔑 v4 DÜZELTMESİ — yukarıdakiyle aynı gerekçe
A17: DefCollateralEligibleCurrency | B17: Tanım alt tablosu | C17: composite PK (Id yok) | D17: ❌ | E17: DefinitionId + CurrencyCode
A18: DefCollateralCashTerms | B18: Tanım alt tablosu (1:0..1) | C18: PK = FK (Id yok) | D18: ❌ | E18: DefinitionId paylaşımlı PK
A19: DefCollateralSettlementMap | B19: Tanım alt tablosu | C19: bigint IDENTITY | D19: ❌
A20: DefCollateralSecurityRule | B20: Tanım alt tablosu | C20: bigint IDENTITY | D20: ❌
A21: DefCollateralSecurityISIN | B21: Tanım alt tablosu | C21: composite PK (Id yok) | D21: ❌ | E21: DefinitionId + ISIN
A22: DefCollateralSecurityTerms | B22: Tanım alt tablosu (1:0..1) | C22: PK = FK (Id yok) | D22: ❌
A23: TxnCollateral | B23: 🔴 İşlem başlığı (flow) | C23: 🔴 DefNumberGen — IDENTITY DEĞİL | D23: ✅ ZORUNLU | E23: MM kuralı: Txn* tablosunda Id sayaçtan gelir (db-script.md §6)
A24: TxnCollateralCash | B24: İşlem alt tipi (1:1) | C24: PK = FK TxnId (Id yok) | D24: ❌ | E24: TxnMMDetail emsali — detayın History'si yok
A25: TxnCollateralSecurity | B25: İşlem alt tipi (1:1) | C25: PK = FK TxnId (Id yok) | D25: ❌
A26: TxnCollateralValuation | B26: Append-only snapshot | C26: bigint IDENTITY | D26: ❌ (zaten immutable) | E26: db-script.md: log/append-only tablo IDENTITY olur, DefNumberGen istemez
A27: TxnCollateralLimit | B27: Append-only snapshot | C27: bigint IDENTITY | D27: ❌
A28: TxnCollateralPaymentInstruction | B28: Versiyonlu talimat | C28: bigint IDENTITY | D28: ❌ | E28: Sürüm artışı yeni satır
A29: TxnCollateralMessage | B29: Mesaj başlığı | C29: bigint IDENTITY | D29: ❌
A30: TxnCollateralMessageEvent | B30: Append-only olay | C30: bigint IDENTITY | D30: ❌
A31: CollateralAuditLog | B31: Append-only log | C31: bigint IDENTITY | D31: ❌ | E31: ⚠️ MM'de polymorphic audit tablosu emsali YOK (bkz açık noktalar)
A32: TxnCollateralPosition | B32: 🔴 Bakiye projeksiyonu — ZORUNLU | C32: composite PK (Id yok) | D32: ❌ | E32: v2'de "opsiyonel" idi; eşzamanlı Decrease kontrolü için zorunlu oldu
A34: 🔴 Açık noktalar — karar bekliyor
A35: # | B35: Konu | C35: Durum
A36: 1 | B36: CollateralAuditLog deseni | C36: MM her tabloya `<Tablo>History` + trigger yazıyor, tek polymorphic audit tablosu kullanmıyor. Doküman tek tablo istiyor. İkisi birlikte de olabilir (History = satır bazlı, AuditLog = olay/korelasyon bazlı). Karar senin.
A37: 2 | B37: Status / LifecycleStatus ↔ StateId | C37: StateId maker-checker onay durumunu taşır. Annex/Definition için ayrı Status kaldırıldı; kullanılabilirlik `(StateId & 2) = 2 AND IsEnabled = 1` ile belirlenir. TxnCollateral.LifecycleStatus ise ekonomik/settlement yaşam döngüsü olarak ayrı kalır.
A38: 3 | B38: Fiziksel FK constraint | C38: MM emsal script’inde fiziksel FK sınırlıdır; ilişkiler Excel’de açık FK → hedef PK eşleşmesi ve EF modeli seviyesinde gösterilir. DDL’de fiziksel FK yazılıp yazılmayacağı ayrı karar olarak korunur.
A39: 4 | B39: DB adı | C39: `NetTrexCollateral` varsayıldı. Değişirse yalnız script'teki USE satırı değişir.
A40: 5 | B40: Security / SSI / Account / Rating master | C40: MM'de yok. Collateral'ın en büyük dış bağımlılığı — ayrı modül mü, Collateral içinde mi tanımlanacak (bkz 00_Iliskiler B).

Sheet 00_Tip_Kurallari
A1: Tip Kuralları (NetTrexMM fiziksel şemasından ölçüldü)
A2: Ofis standardı. Bu Excel'deki her kolon bu kurallara göre tiplenmiştir.
A4: Veri türü | B4: Tip | C4: Kural / gerekçe
A5: Primary key (Id) | B5: bigint | C5: 🔴 Ofis kuralı: tüm PK'ler long/bigint. MM'de eski tablolar int (TxnTawarruq.Id int) ama aktif migrasyon bigint yönünde — emsal: Örnek_Scriptler/4-NetTrexMM-TxnMmDailyCalculation-TxnMmId-long.sql
A6: Foreign key kolonu | B6: bigint (iç) / int (MM master) | C6: Collateral içi FK'ler bigint. MM'in mevcut master tablolarına (CusCustomer, PrfPortfolio, SettlementType) giden FK'ler o tablonun gerçek Id tipinde = int
A7: Para / tutar / değer | B7: decimal(38,10) | C7: MM fiziksel standardı (62 kolon). 🔴 decimal(38,2) MM'de FİZİKSEL OLARAK YOK. 2 ondalık kuralı DB'de değil validator'da
A8: Fiyat / nominal | B8: decimal(38,10) | C8: Tutarla aynı bucket
A9: FX kuru | B9: decimal(38,10) | C9: MM: FXRateDetail.*Rate, TxnSync.Rate = 38,10
A10: Oran / yüzde / haircut (0..1) | B10: decimal(18,10) | C10: MM: TaxRate.Rate, PremiumPercent, Spread = 18,10
A11: 🔴 float / double / real | B11: KULLANILMAZ | C11: Ofis kuralı: finansal hiçbir alanda float/double yok — yalnız decimal
A12: Boolean | B12: bit | C12: Kolon adı Is* (durum) veya Send*/Use* (eylem). NOT NULL + DEFAULT (0) tercih edilir
A13: İş tarihi (TradeDate, ValueDate, ValidFrom) | B13: date | C13: MM: 98 kolon date
A14: Zaman damgası / audit | B14: datetime | C14: MM: 117 kolon datetime. datetime2 yalnız HangFire'da. Kolon soneki ...Date (_at/Timestamp kalıbı YOK)
A15: Döviz kodu | B15: nvarchar(3) | C15: Ccy/CurrencyCode bucket'ı
... A21: Enum / sabit kod kümesi | B21: nvarchar(n) veya int | C21: MM ikisini de kullanıyor: lookup tablosu varsa <X>Id int FK, yoksa kısa kod nvarchar. Kolon yorumunda değer listesi yazılır (db-script.md §5)

Sheet 00_Sabitler
A1: Sabitler ve Kod Listeleri
A3: A) StateId bitmask — MM FlowState (tüm maker-checker tablolarında ortak)
A4: Değer | B4: Ad | C4: Anlamı
A5: 1 | B5: Rejected | C5: Reddedildi biti
A6: 2 | B6: Verified | C6: Onaylandı biti
A7: 4 | B7: Deleted | C7: Silindi biti
A8: 8 | B8: Edited | C8: Düzenlendi biti
A9: 16 | B9: Input | C9: Girildi biti
A10: 16 | B10: Input | C10: Girildi, onaysız
A11: 18 | B11: Input+Verified | C11: 🔑 Onaylı, aktif kayıt
A12: 17 | B12: Input+Rejected | C12: Reddedilmiş
A13: 20 | B13: Input+Deleted | C13: Silme talebi
A14: 22 | B14: Input+Verified+Deleted | C14: Onaylıydı, silindi
A15: 24 | B15: Input+Edited | C15: Düzenleme halinde
A16: 4112 | B16: (özel) WaitingApproval | C16: Tawarruq'ta çift-verify için açılmış özel state — Collateral çift verify isterse emsal bu
A18: B) FlowTransition ActionId değerleri (TxnTawarruq flow emsalinden)
A19: ActionId | B19: Eylem
A20: 2 | B20: Create (initial → Input)
A21: 4 | B21: Update
A22: 8 | B22: Delete
A23: 16 | B23: Verify
A24: 32 | B24: Reject
A26: C) Doküman kod listeleri — C# enum / nvarchar sabit değerleri
A27: Alan | B27: Değerler | C27: Kullanıldığı tablo(lar)
A28: Direction / EligibilityDirection | B28: BOTH · POST_ONLY · RECEIVE_ONLY | C28: DefCollateralAnnex, DefCollateral
A29: ~~Status~~ → IsEnabled bit | B29: 🔑 v4'te KALDIRILDI. DRAFT≈StateId 16 · ACTIVE≈StateId 18 (tekrar) · INACTIVE→ IsEnabled = 0 | C29: DefCollateralAnnex, DefCollateral
A30: CollateralType | B30: CASH · SECURITY | C30: DefCollateral, TxnCollateral
A31: MarginType | B31: VM · IM · IA · OTHER | C31: DefCollateralAnnexProductScope, TxnCollateral, TxnCollateralPosition
A32: Party | B32: OWN · COUNTERPARTY | C32: DefCollateralAnnexMarginRule
A33: RoundingMethod | B33: NEAREST · UP · DOWN | C33: DefCollateralAnnexMarginRule
A34: TransactionType | B34: INCREASE · DECREASE | C34: TxnCollateral, DefCollateralSettlementMap (v4: PaymentInstruction.ActiveFlow kaldırıldı, parent'tan okunur)
A35: LifecycleStatus | B35: DRAFT · VALIDATED · VERIFIED · MESSAGE_PENDING · MESSAGE_GENERATED · SENT · ACCEPTED · SETTLED · FAILED · CANCELLED · REVERSED | C35: TxnCollateral
A36: RateType | B36: FLOATING · FIXED · INTEREST_FREE | C36: DefCollateralCashTerms
A37: CompoundingMethod | B37: DAILY_COMPOUNDED · SIMPLE · NONE | C37: DefCollateralCashTerms
A38: DayCount | B38: ACT_360 · ACT_365 · THIRTY_360 | C38: DefCollateralCashTerms
... A56: Channel (audit) | B56: UI · API · BATCH · ADAPTER | C56: CollateralAuditLog
A58: D) FrameworkParameter satırları (NetTrexCommon — sp_FrameworkAddParameter ile)
A59: OptionPath | B59: OptionName | C59: Örnek değer | D59: Ne işe yarar
A60: Collateral | B60: Module.IsEnabled | C60: true | D60: Modül kill-switch (MM'in InterbankLoan:Enabled emsali)
A61: Collateral | B61: DefaultPortfolioPath | C61: 0/1/2/0/176/ | D61: 🔑 Portföy parametresi Code değil PATH taşır (PrfPortfolio.Code tekil değil)
A62: Collateral | B62: StaleRateToleranceMin | C62: 60 | D62: Kur/fiyat yaşı eşiği (AC-36)
A63: Collateral | B63: MtaDeviationPolicy | C63: Warning | D63: MTA/Rounding sapması: Warning | Override | Block (doküman §8.6)
A64: Collateral | B64: AllowNegativeBalance | C64: false | D64: Decrease bakiyeyi aşabilir mi (doküman §7.3)
D65: ⚠️ sp_FrameworkAddParameter: @OptionName sınırı 50 karakter · mevcut değeri EZMEZ · boş değer yazılamaz

Sheet 00_DB_Nesneleri
A1: Tablo Dışında Üretilmesi Gereken DB Nesneleri
A2: Kaynak: .ai-agent/skills/db-script.md + NetTrex.MM/.ai-agent/imports/Örnek_Scriptler/ (Tawarruq emsali). Script üretilirken bu liste eksiksiz uygulanır.
A4: # | B4: Nesne | C4: Hangi DB | D4: Hangi tablolar için | E4: Kalıp / örnek
A5: 1 | B5: History tablosu | C5: NetTrexCollateral | D5: DefCollateralAnnex, DefCollateral, TxnCollateral (maker-checker/StateId taşıyan 3 tablo) | E5: `<Tablo>History`: [HistoryId] bigint IDENTITY(1,1) PK + ana tablonun TÜM kolonları AYNI SIRADA. PK adı: PK_<Tablo>History
A6: 2 | B6: Trigger | C6: NetTrexCollateral | D6: Yukarıdaki 3 tablo | E6: 🔑 `CREATE OR ALTER TRIGGER [dbo].[<Tablo>Trigger] ON [dbo].[<Tablo>] FOR INSERT, UPDATE AS BEGIN SET NOCOUNT ON; INSERT INTO [dbo].[<Tablo>History] ([Kolon1],[Kolon2],…) SELECT [Kolon1],[Kolon2],… FROM inserted; END` — 🔴 **AÇIK KOLON LİSTESİ** kullan (TxnMMTrigger kalıbı). `SELECT * FROM inserted` eski kuşak (PrdProductDefinitionTrigger) ve kolon sırasına bağımlı — kullanma. Trigger batch'in İLK satırı olmalı
A7: 3 | B7: DefNumberGen satırı | C7: NetTrexCollateral | D7: Yalnız TxnCollateral | E7: DefNumberGen yalnız TxnCollateral.Id için açılır: Definition = 'Txn Collateral Id'. DefCollateralAnnex.Id ve DefCollateral.Id dahil diğer surrogate Id kolonları bigint IDENTITY(1,1); composite ve PK=FK tablolarda ayrı Id yoktur.
A8: 4 | B8: DefRefNumGen / LogicalReference tipi | C8: NetTrexCollateral | D8: TxnCollateral | E8: LogicalReference üretimi ayrı sayaç (sp_GetNewRefNumber, günlük sıfırlanır). LogicalReferenceType satırı + prefix (ör. TCL) tanımlanmalı
A9: 5 | B9: FlowState / FlowSet / FlowRequestMap / FlowTransition | C9: NetTrexCollateral | D9: TxnCollateral (maker-checker akışı) | E9: Emsal: Örnek_Scriptler/6-NetTrexMM-Tawarruq.sql satır 432-594. FlowSet (ör. "CollateralTransactionFlow") + 15-17 FlowTransition satırı (Input 16 → Verify 18 → Delete 20/22 → Edit 24). Çift verify istenirse ek FlowState + FlowDynamicRule
A10: 6 | B10: DefCountMonitoring satırı | C10: 🔴 NetTrexCommon | D10: 🔑 TABLO başına değil, EKRAN başına (en çok 3) | E10: Ölçüldü (30 satır var): Id = MAX(Id)+1 (IDENTITY DEĞİL) · ScreenName nvarchar(100) ör. 'Collateral Transactions' · Query = 'EXEC sp_UnverifiedDataCount_<Ekran> @CurrentUserId' · ScreenUrl = 'general/<Controller>/Index' · Connection = 'Connection' (literal) · DefaultUnverifiedStateId = '3' (nvarchar) · State = 1 (0 = kapalı)
A11: 7 | B11: sp_UnverifiedDataCount_<Ekran> | C11: 🔴 NetTrexCommon | D11: 🔑 EKRAN başına 1 adet (tablo başına DEĞİL) | E11: Ölçüldü: Common'da 30 adet var, modül DB'lerinde YOK. EXEC('CREATE PROCEDURE …') ile kurulur (GO sorunu). Gövde: `SELECT @HavePermission = dbo.fn_HasPermissionWithUserId(@CurrentUserId, '<Ekran>\_%')` + cross-DB sayım `FROM NetTrexCollateral.dbo.<Tablo> WITH (NOLOCK) WHERE (StateId & 2) <> 2 AND (StateId & 1) <> 1` · yetkisizse -1 döner
A12: 7b | B12: 🚫 Modül DB'sine SP YAZMA | C12: NetTrexCollateral | D12: — | E12: Ölçüldü: NetTrexMM'de 125 tabloya karşılık yalnız 9 SP var ve hiçbiri 'her tablo için açılan' türden değil (2'si sayaç, kalanı legacy entegrasyon/rapor). 🔑 Yeni tablo açmak SP açmayı GEREKTİRMEZ. İş mantığı C# handler/DataManager'da
A13: 7c | B13: 🚫 Function YAZMA | C13: NetTrexCollateral | D13: — | E13: Ölçüldü: 28 scalar + 1 TVF var, hepsi 2020-2025 legacy finans kütüphanesi (fn_Accrual, fd_LgDt, fn_ConvertCCY…), modül başına üretilmiyor. Gerekirse MEVCUT fonksiyonları çağır, yenisini yazma
A14: 8 | B14: FrameworkParameter satırları | C14: 🔴 NetTrexCommon | D14: — | E14: exec [dbo].[sp_FrameworkAddParameter] '<Path>','<Name>','<Value>' — elle INSERT YASAK. Liste: 00_Sabitler D bölümü
A15: 9 | B15: FrameworkMenu satırları | C15: 🔴 NetTrexCommon | D15: 3 ekran | E15: MenuKey ile IF NOT EXISTS. 🔴 Menü Redis'te ModuleMenu:{UserId} altında 8 saat cache'li — script sonrası flush notu şart
A16: 10 | B16: Permission (sp_FrameworkAddPermission) | C16: NetTrexCommon | D16: 🔴 YALNIZ Trex.WebUI ekranı yapılırsa | E16: Collateral Micro UI olarak yapılacaksa permission satırı YAZILMAZ (db-script.md §4). Micro UI'da erişim menü üzerinden
A17: 11 | B17: Index'ler | C17: NetTrexCollateral | D17: Tümü | E17: Bkz 00_Constraint_Index sheet'i
A18: 12 | B18: Bakiye güncelleme (TxnCollateralPosition) | C18: NetTrexCollateral | D18: TxnCollateral Verify akışı | E18: 🔴 Eşzamanlı Decrease'i önlemek için: pozisyon satırı Verify ile AYNI transaction içinde `WITH (UPDLOCK, ROWLOCK)` ile okunup güncellenir — DefNumberGen'in sp_GetNewNumbers'da kullandığı kanıtlanmış kalıbın aynısı

Sheet 00_Constraint_Index
A1: Constraint ve Index Listesi (ev isimlendirmesiyle)
A2: İsim kalıpları (db-script.md §5): PK_<Tablo> · UQ_<Tablo>_<Kolon> · IX_<Tablo>_<Kolon> · DF_<Tablo>_<Kolon> · <Tablo>Trigger. FK kalıbı: FK_<Tablo>_<HedefTablo>_<Kolon> (EF default) — ⚠️ MM emsal script'inde fiziksel FK YAZILMIYOR, karar 00_Genel_Bakis açık nokta #3.
A4: A) Primary key
A5: Tablo | B5: Constraint adı | C5: Kolon(lar) | D5: Not
A6: DefCollateralAnnex | B6: PK_DefCollateralAnnex | C6: Id | D6: CLUSTERED
A7: DefCollateralAnnexProductScope | B7: PK_DefCollateralAnnexProductScope | C7: Id
A8: DefCollateralAnnexMarginRule | B8: PK_DefCollateralAnnexMarginRule | C8: Id
A9: DefCollateral | B9: PK_DefCollateral | C9: Id
A10: DefCollateralEligibleCurrency | B10: PK_DefCollateralEligibleCurrency | C10: DefinitionId, CurrencyCode | D10: Composite — aynı para birimi tekrar edemez
A11: DefCollateralCashTerms | B11: PK_DefCollateralCashTerms | C11: DefinitionId | D11: PK = FK (1:0..1)
A12: DefCollateralSettlementMap | B12: PK_DefCollateralSettlementMap | C12: Id
A13: DefCollateralSecurityRule | B13: PK_DefCollateralSecurityRule | C13: Id
A14: DefCollateralSecurityISIN | B14: PK_DefCollateralSecurityISIN | C14: DefinitionId, ISIN | D14: Composite
A15: DefCollateralSecurityTerms | B15: PK_DefCollateralSecurityTerms | C15: DefinitionId | D15: PK = FK
A16: TxnCollateral | B16: PK_TxnCollateral | C16: Id | D16: CLUSTERED · Id DefNumberGen'den
A17: TxnCollateralCash | B17: PK_TxnCollateralCash | C17: TxnId | D17: PK = FK
A18: TxnCollateralSecurity | B18: PK_TxnCollateralSecurity | C18: TxnId | D18: PK = FK
A19: TxnCollateralValuation | B19: PK_TxnCollateralValuation | C19: Id
A20: TxnCollateralLimit | B20: PK_TxnCollateralLimit | C20: Id
A21: TxnCollateralPaymentInstruction | B21: PK_TxnCollateralPaymentInstruction | C21: Id
A22: TxnCollateralMessage | B22: PK_TxnCollateralMessage | C22: Id
A23: TxnCollateralMessageEvent | B23: PK_TxnCollateralMessageEvent | C23: Id
A24: CollateralAuditLog | B24: PK_CollateralAuditLog | C24: Id
A25: TxnCollateralPosition | B25: PK_TxnCollateralPosition | C25: DefinitionId, MarginType, AssetCode | D25: Composite — bakiye kırılımının kendisi
A26: <Tablo>History (3 adet) | B26: PK_<Tablo>History | C26: HistoryId | D26: bigint IDENTITY
A28: B) Unique index — iş kuralı taşıyanlar 🔴 (ad kalıbı: UQ_<Tablo>_<İlkKolon> — MM'de composite UQ adı YALNIZ ilk kolonu taşıyor, ölçüldü: UQ_FXRateDetail_FXRateId 3 kolonluk)
A29: Index adı | B29: Tablo (kolonlar) | C29: Hangi iş kuralını/kabul kriterini karşılıyor
A30: UQ_DefCollateralAnnex_AnnexCode | B30: DefCollateralAnnex (AnnexCode, RevisionNo) | C30: AC-37 — aynı iş kodunda revizyon tekilliği
A31: UQ_DefCollateral_CollateralCode | B31: DefCollateral (CollateralCode, RevisionNo) | C31: AC-37 — aynı Collateral Code'da revizyon tekilliği
A32: UQ_TxnCollateral_TransactionReference | B32: TxnCollateral (TransactionReference) | C32: İşlem referansı tekilliği
A33: UQ_TxnCollateral_LogicalReference | B33: TxnCollateral (LogicalReference) | C33: ✅ MM emsali birebir: UQ_TxnMM_LogicalReference, UQ_TxnTawarruq_LogicalReference
A34: UQ_TxnCollateral_SourceSystem | B34: TxnCollateral (SourceSystem, ExternalReference) | C34: 🔴 AC-35 — harici kaynak duplicate engeli. ⚠️ MM'de FILTERED index HİÇ YOK (5/5 filtered değil). İki seçenek: (a) bilinçli sapma → WHERE ExternalReference IS NOT NULL filtered index, (b) ev deseni → kolonları NOT NULL DEFAULT('') yapıp düz UQ. 🔑 Karar gerekiyor
A35: UQ_TxnCollateralLimit_TxnId | B35: TxnCollateralLimit (TxnId, SnapshotStage) | C35: Aynı aşama için duplicate limit snapshot engeli
A36: UQ_TxnCollateralPaymentInstruction_TxnId | B36: TxnCollateralPaymentInstruction (TxnId, InstructionVersion) | C36: Talimat sürüm tekilliği
A37: UQ_TxnCollateralMessage_IdempotencyKey | B37: TxnCollateralMessage (IdempotencyKey) | C37: 🔴 AC-12/AC-17 — duplicate ödeme/settlement mesajı engeli
A38: UQ_TxnCollateralMessage_UETR | B38: TxnCollateralMessage (UETR) | C38: ⚠️ UETR nullable → ya filtered index (ev deseninden sapma) ya da unique'ten vazgeçip IX kullan
A39: UQ_DefCollateralAnnexMarginRule_ProductScopeId | B39: DefCollateralAnnexMarginRule (ProductScopeId, Party, CurrencyCode) | C39: Aynı ürün kapsamı + taraf + para birimi için duplicate kuralı önler; geçerlilik parent Annex revizyonundan gelir.
A41: C) Non-unique index — performans
A42: Index adı | B42: Tablo (kolonlar) | C42: Neden
A43: IX_TxnCollateral_DefinitionId_ValueDate | B43: TxnCollateral (DefinitionId, ValueDate) | C43: Tarihçe + running balance sorgusu (doküman §10.23)
A44: IX_TxnCollateral_StateId | B44: TxnCollateral (StateId) | C44: sp_UnverifiedDataCount sayımı + onay bekleyen listesi
A45: IX_TxnCollateral_CustomerId | B45: TxnCollateral (CustomerId) | C45: Karşı taraf bazlı sorgu
A46: IX_TxnCollateralCash_CurrencyCode | B46: TxnCollateralCash (CurrencyCode) | C46: Para birimi bazlı bakiye
A47: IX_TxnCollateralSecurity_ISIN | B47: TxnCollateralSecurity (ISIN) | C47: ISIN bazlı bakiye
A48: IX_TxnCollateralValuation_TxnId_Stage | B48: TxnCollateralValuation (TxnId, SnapshotStage) | C48: Snapshot okuma
A49: IX_TxnCollateralMessageEvent_MessageId_Occurred | B49: TxnCollateralMessageEvent (MessageId, OccurredDate) | C49: Kanal yaşam döngüsü/mutabakat
A50: IX_CollateralAuditLog_Aggregate | B50: CollateralAuditLog (AggregateType, AggregateId) | C50: Polymorphic audit okuma
A51: IX_CollateralAuditLog_CorrelationId | B51: CollateralAuditLog (CorrelationId) | C51: Uçtan uca izleme
A52: IX_DefCollateral_CollateralCode | B52: DefCollateral (CollateralCode, IsEnabled) | C52: Aktif tanım arama (v4: Status kolonu kalktı, IsEnabled geldi)
A53: IX_DefCollateralAnnex_CustomerId | B53: DefCollateralAnnex (CustomerId) | C53: Karşı taraf bazlı Annex listesi
A55: D) Default constraint
A56: Constraint adı | B56: Tablo.Kolon | C56: Değer
A57: DF_TxnCollateral_Trader | B57: TxnCollateral.Trader | C57: ('')
A58: DF_TxnCollateral_EconomicVersion | B58: TxnCollateral.EconomicVersion | C58: (1)
A59: DF_TxnCollateralCash_FxAdjustmentRate | B59: TxnCollateralCash.FxAdjustmentRate | C59: (0)
A60: DF_TxnCollateralPaymentInstruction_SendConfirmation | B60: TxnCollateralPaymentInstruction.SendConfirmation | C60: (0)
A61: DF_TxnCollateralPaymentInstruction_SendPayment | B61: TxnCollateralPaymentInstruction.SendPayment | C61: (0)
A62: DF_TxnCollateralPaymentInstruction_SendNoticeToReceive | B62: TxnCollateralPaymentInstruction.SendNoticeToReceive | C62: (0)
A63: DF_TxnCollateralMessage_RetryCount | B63: TxnCollateralMessage.RetryCount | C63: (0)
A64: DF_<Tablo>_StateId | B64: StateId olan HER tablo | C64: ((18)) — framework "yeni/doğrulanmamış" durumu. Ölçüldü: 4 tabloda bu default var
A65: DF_<Tablo>_StateDate | B65: StateDate olan her tablo | C65: (getdate()) — ölçüldü: 7 kullanım
A66: DF_<Tablo>_StateMaker | B66: StateMaker olan her tablo | C66: ('system') — ölçüldü: 2 kullanım
A67: DF_<Tablo>_CreatedBy | B67: CreatedBy | C67: (N'') — NULL yerine boş string (ev tercihi)
... A70: 🔴 İsimsiz DEFAULT | B70: — | C70: ASLA yazma. MM'de 1 hata var: DF__TxnTawarr__Exter__458AE82D (SQL Server üretti çünkü ad verilmemiş) — kopyalanmamalı
A72: E) CHECK constraint — ⚠️ KARAR GEREKİYOR
A73: Konu | B73: Durum
A74: Doküman isteği | B74: Doküman §10.24 bol CHECK istiyor: Status IN (…), Amount > 0, ValidTo >= ValidFrom, oran 0..1, "exactly one subtype", directional SSI pair
A75: 🔴 MM gerçeği (ÖLÇÜLDÜ) | B75: NetTrexMM'de sys.check_constraints = **0 satır**. 125 tabloda TEK BİR CHECK constraint yok. Tüm kontroller FluentValidation + domain katmanında
A76: Varsayılan karar | B76: 🔑 **CHECK YAZMA** — ev konvansiyonu bu. Bu Excel'deki "> 0", "0..1", "ValidTo >= ValidFrom" gibi ifadeler DB constraint'i değil, SERVİS KATMANI validasyon kuralıdır (F bölümüne bak)
A77: Sapmak istenirse | B77: MM'de emsal olmadığı için isim kalıbı sıfırdan tanımlanır (`CK_<Tablo>_<Kural>`) ve bu karar yazılı hale getirilmelidir — ileride MM'e bakıp kopyalayan kimse CHECK görmeyecek
A79: F) Servis katmanı invariant'ları (DB zorlayamaz / zorlamayacak)
A80: Invariant | B80: Nerede uygulanır | C80: Kabul kriteri
A81: Exactly one subtype: CollateralType=CASH → yalnız TxnCollateralCash satırı; SECURITY → yalnız TxnCollateralSecurity | B81: Transaction servisi (Create/Verify) | C81: Doküman §10.24
A82: Directional SSI: INCREASE → TheySend+WeReceive zorunlu; DECREASE → WeSend+TheyReceive zorunlu | B82: Verify validasyonu | C82: AC-29, AC-32, AC-33
A83: Decrease kullanılabilir bakiyeyi aşamaz | B83: Verify — TxnCollateralPosition UPDLOCK ile okunur | C83: AC-09, AC-38
A84: VERIFIED sonrası ekonomik kolonlara UPDATE yok — düzeltme reversal ile | B84: Transaction servisi + flow (FlowTransition) | C84: AC-18
A85: Aktif revizyon dönemleri çakışamaz (aynı kod için) | B85: Annex/Definition servisi | C85: AC-37
A86: Transaction Type ↔ Annex Direction uyumu | B86: Verify validasyonu | C86: AC-21, AC-22, AC-32, AC-33
A87: Idempotent re-verify: aynı ekonomik sürüm için ikinci mesaj üretilmez | B87: Message servisi (IdempotencyKey) | C87: AC-12, AC-17

Sheet 00_Referans_Kopyalari
A1: Referans Veri Kopyaları — NetTrexCollateral'de AÇILMASI ZORUNLU Tablolar
A2: 🔴 ÖLÇÜLDÜ: NetTrexCommon master, her modül DB'si referans verisinin KENDİ kopyasını tutuyor (Common↔MM kesişimi 44 tablo) ve Kafka ile besleniyor. Her modül YALNIZ ihtiyacı kadarını açıyor (MM 24 topic, OptionsFX 11). Kanıt: Tawarruq script'i aynı kolonu 5 ayrı DB'nin CusCustomer'ına ekliyor.
A4: 🔴 3 ZORUNLU KURAL (kopya tablolar normal tablolardan FARKLI davranır)
A5: Kural | B5: Gerekçe
A6: Id IDENTITY DEĞİL — EF config'te `.ValueGeneratedNever()` açıkça yazılır | B6: Common'ın Id'si birebir taşınıyor. Emsal: PortfolioConfiguration, MarketCustomerMapConfiguration
A7: DefNumberGen sayacı AÇILMAZ | B7: Id dışarıdan geliyor, üretilmiyor
A8: History + Trigger YAZILMAZ | B8: Tarihçe Common'da (CustomerHistory vb.). MM'in 9 History tablosunun hiçbiri referans kopyası değil
A10: KATMAN A — çekirdek, tartışmasız (12 tablo · 13 topic · 12 handler)
A11: Tablo (NetTrexCollateral) | B11: Common'daki adı | C11: Kafka topic | D11: Handler | E11: Collateral neden ihtiyaç duyuyor
A12: CusCustomer | B12: Customer | C12: customer-insert | D12: CustomerCreateHandler | E12: Counterparty — Annex/Definition/Transaction'ın hepsinde FK
A13: PrfPortfolio | B13: Portfolio | C13: portfolio-insert | D13: PortfolioCreateHandler | E13: TxnCollateral.PortfolioId
A14: Currency | B14: Currency | C14: currency-insert | D14: CurrencyCreateHandler | E14: Her tutar/değerleme kolonunun para birimi
A15: DefDateBasis | B15: DateBasis | C15: datebasis-insert | D15: DateBasisCreateHandler | E15: Cash faiz şartları (DayCount)
A16: Calendar | B16: Calendar | C16: calendar-insert + calendar-delete | D16: CalendarCreateHandler + CalendarDeleteHandler | E16: ValueDate/BusinessDayRule hesabı
A17: Holiday | B17: Holiday | C17: holiday-insert + holiday-delete | D17: HolidayCreateHandler + HolidayDeleteHandler | E17: Tatil kaydırma (AC-36 cut-off)
A18: HalfWorkingDay | B18: HalfWorkingDay | C18: halfworkingday-insert | D18: CreateHalfWorkingDayHandler | E18: Yarım gün takvimi
A19: DefCountry | B19: Country | C19: country-insert | D19: CreateCountryHandler | E19: DefCollateralSecurityRule.CountryOfRiskCode
A20: DefCorporateType + DefCorporateDetailType | B20: CorporateType | C20: corporate-type-insert | D20: CreateCorporateTypeHandler ⚠️ TEK handler → İKİ tablo | E20: Karşı taraf tüzel kişilik tipi
A21: FXRate + FXRateDetail | B21: FXRate(Detail) | C21: fxrate-insert, fxratedetail-insert, fxratedetail-delete | D21: FxRateInsertHandler, FxRateDetailInsertHandler, FxRateDetailDeleteHandler | E21: 🔑 FX dönüşümü + haircut hesabının temeli (doküman §8.1)
A23: KATMAN B / C / D — koşullu
A24: Katman | B24: Tablolar | C24: Koşul
A25: B (+2) | B25: ExternalCustomerMap, ExternalUserMap | C25: Collateral Fimple/muhasebe entegrasyonuna girerse. Faz-1'de muhasebe KAPSAM DIŞI (doküman §1.1) → muhtemelen gerekmez
A26: C (+5) | B26: InterestRate + InterestRateDetail · Chart + Point · Market + MarketCustomerMap + DefTxnType | C26: ⚠️ TAHMİN: NPV/iskonto hesabı veya eğri/fiyat verisi gerekirse. Collateral değerlemesi fiyat × nominal × haircut olduğu için muhtemelen GEREKMİYOR
A27: D — AÇMA | B27: TaxTax/TaxRate/TaxRule/TaxType · DefBitMask · CusSIC · Branch · CurrencyPair · DefTaxOffice · DefLegalVehicle · UsrUserLayout … | C27: 🔴 MM'de Tax topic'leri KAPALI (TaxRule tablosu 0 satır), diğerlerinin Consumer'ı hiç yok — seed/legacy taşıma
A29: Tablo sayısına etkisi
A30: Senaryo | B30: Referans kopyası | C30: Handler | D30: Topic | E30: Collateral toplam tablo
A31: Katman A (önerilen) | B31: +12 | C31: 12 | D31: 13 | E31: 20 iş tablosu + 12 = **32**
A32: A + B (Fimple'lı) | B32: +14 | C32: 14 | D32: 15 | E32: 34
A33: Tam MM paritesi | B33: +19 | C33: 20 | D33: 24 | E33: 39
A35: ⚠️ MM'in yapmadığı, Collateral'ın yapabileceği iyileştirme
A36: Sorun (MM'de ölçüldü) | B36: Öneri
A37: Consumer handler'ları doğrulama YAPMIYOR — exists-check → insert/update, o kadar. Bedeli ölçülmüş veri kalitesi sorunları: Currency.IsoCode tutarsız · Currency.BasisCode='SPOT' (DefDateBasis'te böyle bir değer yok) · CusCustomer.ExternalCustomerId mükerrer | B37: Collateral consumer'ına basit bir doğrulama katmanı ekle (zorunlu alan + FK varlık kontrolü + log). MM'in yapmadığı bir iyileştirme olur
A38: Topic adları appsettings'te değil, RequestCreatorFactory.cs içinde hardcode dictionary; her anahtar için ayrı Thread | B38: Aynı deseni kopyala (tutarlılık için) ama topic listesini sabit sınıfa almayı değerlendir

Sheet 00_Iliskiler
A1: Tablolar Arası İlişkiler (FK → PK)
A2: 🔴 ÖLÇÜLDÜ: NetTrexMM'de 125 tabloya karşılık yalnız 14 fiziksel FK var (hepsi referans/tanım tablolarına, hepsi NO_ACTION) — işlem/detay/history tabloları arasında FK YOK, son 2 yılın hiçbir script'inde FOREIGN KEY geçmiyor. İlişkiler EF model tarafında (HasOne/WithMany) tanımlı. Aşağıdaki FK adları, yazılmasına karar verilirse kullanılacak ev kalıbıdır: FK_<BağımlıTablo>_<HedefTablo>_<FkKolonu> (EF default, 14/14 uyuyor) · ON DELETE yazma (NO_ACTION default) · CASCADE ev deseninde YOK.
A4: A) İç ilişkiler — Collateral'ın kendi tabloları
A5: Parent Tablo | B5: Parent PK | C5: Child Tablo | D5: Child FK Kolonu | E5: FK Constraint adı (yazılırsa) | F5: Kardinalite / not
A6: DefCollateralAnnex | B6: Id | C6: DefCollateralAnnexProductScope | D6: AnnexId | E6: FK_DefCollateralAnnexProductScope_DefCollateralAnnex_AnnexId | F6: 1:N · ON DELETE NO ACTION
A7: DefCollateralAnnexProductScope | B7: Id | C7: DefCollateralAnnexMarginRule | D7: ProductScopeId | E7: FK_DefCollateralAnnexMarginRule_DefCollateralAnnexProductScope_ProductScopeId | F7: 1:N
A8: DefCollateralAnnex | B8: Id | C8: DefCollateral | D8: AnnexId | E8: FK_DefCollateral_DefCollateralAnnex_AnnexId | F8: 1:N opsiyonel (nullable — standalone definition)
A9: DefCollateral | B9: Id | C9: DefCollateralEligibleCurrency | D9: DefinitionId | E9: FK_DefCollateralEligibleCurrency_DefCollateral_DefinitionId | F9: 1:N · Cash için en az 1 aktif satır
A10: DefCollateral | B10: Id | C10: DefCollateralCashTerms | D10: DefinitionId | E10: FK_DefCollateralCashTerms_DefCollateral_DefinitionId | F10: 1:0..1 · yalnız CASH
A11: DefCollateral | B11: Id | C11: DefCollateralSecurityRule | D11: DefinitionId | E11: FK_DefCollateralSecurityRule_DefCollateral_DefinitionId | F11: 1:N · Security Scope = Rule
A12: DefCollateral | B12: Id | C12: DefCollateralSecurityISIN | D12: DefinitionId | E12: FK_DefCollateralSecurityISIN_DefCollateral_DefinitionId | F12: 1:N · Security Scope = Specific ISIN
A13: DefCollateral | B13: Id | C13: DefCollateralSecurityTerms | D13: DefinitionId | E13: FK_DefCollateralSecurityTerms_DefCollateral_DefinitionId | F13: 1:0..1 · yalnız SECURITY
A14: DefCollateral | B14: Id | C14: DefCollateralSettlementMap | D14: DefinitionId | E14: FK_DefCollateralSettlementMap_DefCollateral_DefinitionId | F14: 1:N
A15: DefCollateral | B15: Id | C15: TxnCollateral | D15: DefinitionId | E15: FK_TxnCollateral_DefCollateral_DefinitionId | F15: 1:N · 🔴 işlem varken definition silinemez
A16: DefCollateralAnnex | B16: Id | C16: TxnCollateral | D16: AnnexId | E16: FK_TxnCollateral_DefCollateralAnnex_AnnexId | F16: 1:N opsiyonel
... A27: (polymorphic) | B27: — | C27: CollateralAuditLog | D27: AggregateId + AggregateType | E27: ❌ FK yazılamaz | F27: Polymorphic — gerçek FK constraint mümkün değil
A28: B) Dış bağımlılıklar — mevcut MM tabloları vs yeni gerekenler
A29: Kolon(lar) | B29: Hedef | C29: Durum | D29: Not
A30: CustomerId (4 tabloda) | B30: CusCustomer.Id | C30: ✅ MM'de VAR | D30: Counterparty = MM'in Customer kavramı. Tip: int (MM'in mevcut tipi)
A31: CurrencyCode (çok sayıda) | B31: Currency | C31: ✅ MM'de VAR | D31: nvarchar(3) doğal anahtar
A32: PortfolioId | B32: PrfPortfolio.Id | C32: ✅ MM'de VAR | D32: 🔑 Varsayılan portföy parametreden PATH ile çözülür, Code ile değil
A33: SettlementTypeId | B33: SettlementType.Id | C33: ✅ MM'de VAR | D33: Değer kümesi örtüşüyor (Gross/Netting) — yeni tablo AÇMA
A34: PaymentInstructionTypeId | B34: PaymentInstructionType.Id | C34: ✅ MM'de VAR | D34: B2B/A2A/Vostro/A2AD — yeni tablo AÇMA
A35: TraderUserId / StateMaker / CreatedBy | B35: Kullanıcı (nvarchar(80)) | C35: ✅ MM deseni | D35: MM ayrı User tablosuna FK vermiyor, string tutuyor
A36: ProductCode, SubProductCode | B36: Ürün kataloğu | C36: ⚠️ NETLEŞMEDİ | D36: MM'in PrdProductDefinition'ı hazine ürün ailesi (FX/IR/Repo) için yeterli mi?
A37: SettlementAccountId, InterestAccountId | B37: Hesap master | C37: ⚠️ NETLEŞMEDİ | D37: MM'de hesap Fimple'dan geliyor (AccountNumber/GLCode kolonları), ayrı master yok
A38: SsiId (5 kolonda) | B38: SSI master | C38: 🔴 YENİ GEREKLİ | D38: MM'de yok. Collateral içinde mi, ortak modülde mi?
A39: ISIN, SecurityTypeCode, IssuerTypeCode, MinimumRatingCode | B39: Menkul kıymet master | C39: 🔴 YENİ GEREKLİ | D39: Collateral'ın en büyük dış bağımlılığı
A40: SettlementLocationCode | B40: CSD/ICSD kataloğu | C40: 🔴 YENİ GEREKLİ | D40: Takasbank/Euroclear/Clearstream
... A43: CountryOfRiskCode | B43: Ülke kataloğu | C43: ⚠️ MM'de DefCountry var | D43: Kontrol edilmeli

Sheet 00_UML_Diyagram
B1: Collateral DB — UML / ER Diyagramı (canlı: kolonlar tablo sheet'lerinden formülle okunur)
B3: Renk: | C3: Annex grubu | D3: Definition grubu | E3: Txn grubu | F3: Log / polymorphic
AA5: İlişki listesi (canlı — 00_Iliskiler bölüm A'dan okunur) | AF5: Görsel bağlantı anahtarı — FK → PK
B6: =DefCollateralAnnexProductScope!A1 -> DefCollateralAnnexProductScope | G6: =DefCollateralAnnex!A1 -> DefCollateralAnnex | Q6: =TxnCollateralCash!A1 -> TxnCollateralCash | V6: =CollateralAuditLog!A1 -> CollateralAuditLog | AA6: {=_xlfn.LET(_xlpm.d,'00_Iliskiler'!$A$5:$F$60,_xlpm.k,INDEX(_xlpm.d,,1),_xlpm.e,MATCH(TRUE,_xlpm.k="",0)-1,_xlfn.TAKE(_xlfn.CHOOSECOLS(_xlpm.d,1,2,3,4,6),_xlpm.e))} -> Parent Tablo | AB6: Parent PK | AC6: Child Tablo | AD6: Child FK Kolonu | AE6: Kardinalite / not | AF6: Bağlantı | AG6: Açık kolon eşleşmesi (Child.FK → Parent.PK)
B7: Anahtar | C7: ="Kolon / FK hedefi ("&ROWS(_xlfn.ANCHORARRAY(B8))&")" -> Kolon / FK hedefi (6) | D7: Tip | E7: Null | G7: Anahtar | H7: ="Kolon / FK hedefi ("&ROWS(_xlfn.ANCHORARRAY(G8))&")" -> Kolon / FK hedefi (19) | I7: Tip | J7: Null | Q7: Anahtar | R7: ="Kolon / FK hedefi ("&ROWS(_xlfn.ANCHORARRAY(Q8))&")" -> Kolon / FK hedefi (10) | S7: Tip | T7: Null | V7: Anahtar | W7: ="Kolon / FK hedefi ("&ROWS(_xlfn.ANCHORARRAY(V8))&")" -> Kolon / FK hedefi (11) | X7: Tip | Y7: Null | AA7: DefCollateralAnnex | AB7: Id | AC7: DefCollateralAnnexProductScope | AD7: AnnexId | AE7: 1:N · ON DELETE NO ACTION | AF7: R01 | AG7: =IF($AF7="POLY",$AC7&".["&$AD7&"] → polymorphic (fiziksel FK yok)",$AC7&"."&$AD7&" → "&$AA7&"."&$AB7) -> DefCollateralAnnexProductScope.AnnexId → DefCollateralAnnex.Id
B8: {=_xlfn.LET(_xlpm.d,DefCollateralAnnexProductScope!$A$7:$F$79,_xlpm.n,INDEX(_xlpm.d,,1),_xlpm.t,INDEX(_xlpm.d,,2),_xlpm.nl,INDEX(_xlpm.d,,3),_xlpm.c,INDEX(_xlpm.d,,5),_xlpm.f,INDEX(_xlpm.d,,6),_xlpm.pk,ISNUMBER(SEARCH("PK_",_xlpm.c))+ISNUMBER(SEARCH("(PK ile)",_xlpm.c)),_xlpm.fk,(LEFT(_xlpm.f,3)="Def")+(LEFT(_xlpm.f,3)="Txn"),_xlpm.qone,ISNUMBER(SEARCH("UQ1",_xlpm.c)),_xlpm.qtwo,ISNUMBER(SEARCH("UQ2",_xlpm.c)),_xlpm.qthree,ISNUMBER(SEARCH("UQ3",_xlpm.c)),_xlpm.uq,ISNUMBER(SEARCH("UQ",_xlpm.c)),_xlpm.ul,IF(_xlpm.qone,"UQ1",IF(_xlpm.qtwo,"UQ2",IF(_xlpm.qthree,"UQ3","UQ"))),_xlpm.ky,TRIM(IF(_xlpm.pk,"PK ","")&IF(_xlpm.fk,"FK ","")&IF(_xlpm.uq*(_xlpm.pk=0),_xlpm.ul,"")),_xlfn._xlws.FILTER(CHOOSE({1,2,3,4},_xlpm.ky,IF(_xlpm.fk,_xlpm.n&" → "&_xlpm.f,_xlpm.n),_xlpm.t,IF(_xlpm.nl="Yes","NULL","NOT NULL")),(_xlpm.n<>"")*(LEFT(_xlpm.n,1)<>"—")))} -> PK | C8: Id | D8: bigint | E8: NOT NULL | G8: {=_xlfn.LET(_xlpm.d,DefCollateralAnnex!$A$7:$F$80,_xlpm.n,INDEX(_xlpm.d,,1),_xlpm.t,INDEX(_xlpm.d,,2),_xlpm.nl,INDEX(_xlpm.d,,3),_xlpm.c,INDEX(_xlpm.d,,5),_xlpm.f,INDEX(_xlpm.d,,6),_xlpm.pk,ISNUMBER(SEARCH("PK_",_xlpm.c))+ISNUMBER(SEARCH("(PK ile)",_xlpm.c)),_xlpm.fk,(LEFT(_xlpm.f,3)="Def")+(LEFT(_xlpm.f,3)="Txn"),_xlpm.qone,ISNUMBER(SEARCH("UQ1",_xlpm.c)),_xlpm.qtwo,ISNUMBER(SEARCH("UQ2",_xlpm.c)),_xlpm.qthree,ISNUMBER(SEARCH("UQ3",_xlpm.c)),_xlpm.uq,ISNUMBER(SEARCH("UQ",_xlpm.c)),_xlpm.ul,IF(_xlpm.qone,"UQ1",IF(_xlpm.qtwo,"UQ2",IF(_xlpm.qthree,"UQ3","UQ"))),_xlpm.ky,TRIM(IF(_xlpm.pk,"PK ","")&IF(_xlpm.fk,"FK ","")&IF(_xlpm.uq*(_xlpm.pk=0),_xlpm.ul,"")),_xlfn._xlws.FILTER(CHOOSE({1,2,3,4},_xlpm.ky,IF(_xlpm.fk,_xlpm.n&" → "&_xlpm.f,_xlpm.n),_xlpm.t,IF(_xlpm.nl="Yes","NULL","NOT NULL")),(_xlpm.n<>"")*(LEFT(_xlpm.n,1)<>"—")))} -> PK | H8: Id | I8: bigint | J8: NOT NULL | Q8: {=_xlfn.LET(_xlpm.d,TxnCollateralCash!$A$7:$F$80,_xlpm.n,INDEX(_xlpm.d,,1),_xlpm.t,INDEX(_xlpm.d,,2),_xlpm.nl,INDEX(_xlpm.d,,3),_xlpm.c,INDEX(_xlpm.d,,5),_xlpm.f,INDEX(_xlpm.d,,6),_xlpm.pk,ISNUMBER(SEARCH("PK_",_xlpm.c))+ISNUMBER(SEARCH("(PK ile)",_xlpm.c)),_xlpm.fk,(LEFT(_xlpm.f,3)="Def")+(LEFT(_xlpm.f,3)="Txn"),_xlpm.qone,ISNUMBER(SEARCH("UQ1",_xlpm.c)),_xlpm.qtwo,ISNUMBER(SEARCH("UQ2",_xlpm.c)),_xlpm.qthree,ISNUMBER(SEARCH("UQ3",_xlpm.c)),_xlpm.uq,ISNUMBER(SEARCH("UQ",_xlpm.c)),_xlpm.ul,IF(_xlpm.qone,"UQ1",IF(_xlpm.qtwo,"UQ2",IF(_xlpm.qthree,"UQ3","UQ"))),_xlpm.ky,TRIM(IF(_xlpm.pk,"PK ","")&IF(_xlpm.fk,"FK ","")&IF(_xlpm.uq*(_xlpm.pk=0),_xlpm.ul,"")),_xlfn._xlws.FILTER(CHOOSE({1,2,3,4},_xlpm.ky,IF(_xlpm.fk,_xlpm.n&" → "&_xlpm.f,_xlpm.n),_xlpm.t,IF(_xlpm.nl="Yes","NULL","NOT NULL")),(_xlpm.n<>"")*(LEFT(_xlpm.n,1)<>"—")))} -> PK FK | R8: TxnId → TxnCollateral.Id | S8: bigint | T8: NOT NULL | V8: {=_xlfn.LET(_xlpm.d,CollateralAuditLog!$A$7:$F$80,_xlpm.n,INDEX(_xlpm.d,,1),_xlpm.t,INDEX(_xlpm.d,,2),_xlpm.nl,INDEX(_xlpm.d,,3),_xlpm.c,INDEX(_xlpm.d,,5),_xlpm.f,INDEX(_xlpm.d,,6),_xlpm.pk,ISNUMBER(SEARCH("PK_",_xlpm.c))+ISNUMBER(SEARCH("(PK ile)",_xlpm.c)),_xlpm.fk,(LEFT(_xlpm.f,3)="Def")+(LEFT(_xlpm.f,3)="Txn"),_xlpm.qone,ISNUMBER(SEARCH("UQ1",_xlpm.c)),_xlpm.qtwo,ISNUMBER(SEARCH("UQ2",_xlpm.c)),_xlpm.qthree,ISNUMBER(SEARCH("UQ3",_xlpm.c)),_xlpm.uq,ISNUMBER(SEARCH("UQ",_xlpm.c)),_xlpm.ul,IF(_xlpm.qone,"UQ1",IF(_xlpm.qtwo,"UQ2",IF(_xlpm.qthree,"UQ3","UQ"))),_xlpm.ky,TRIM(IF(_xlpm.pk,"PK ","")&IF(_xlpm.fk,"FK ","")&IF(_xlpm.uq*(_xlpm.pk=0),_xlpm.ul,"")),_xlfn._xlws.FILTER(CHOOSE({1,2,3,4},_xlpm.ky,IF(_xlpm.fk,_xlpm.n&" → "&_xlpm.f,_xlpm.n),_xlpm.t,IF(_xlpm.nl="Yes","NULL","NOT NULL")),(_xlpm.n<>"")*(LEFT(_xlpm.n,1)<>"—")))} -> PK | W8: Id | X8: bigint | Y8: NOT NULL | AA8: DefCollateralAnnexProductScope | AB8: Id | AC8: DefCollateralAnnexMarginRule | AD8: ProductScopeId | AE8: 1:N | AF8: R02 | AG8: =IF($AF8="POLY",$AC8&".["&$AD8&"] → polymorphic (fiziksel FK yok)",$AC8&"."&$AD8&" → "&$AA8&"."&$AB8) -> DefCollateralAnnexMarginRule.ProductScopeId → DefCollateralAnnexProductScope.Id
B9: FK | C9: AnnexId → DefCollateralAnnex.Id | D9: bigint | E9: NOT NULL | G9: UQ1 | H9: AnnexCode | I9: nvarchar(50) | J9: NOT NULL | R9: Amount | S9: decimal(38,10) | T9: NOT NULL | W9: AggregateType | X9: nvarchar(40) | Y9: NOT NULL | AA9: DefCollateralAnnex | AB9: Id | AC9: DefCollateral | AD9: AnnexId | AE9: 1:N opsiyonel (nullable — standalone definition) | AF9: R03 | AG9: =IF($AF9="POLY",$AC9&".["&$AD9&"] → polymorphic (fiziksel FK yok)",$AC9&"."&$AD9&" → "&$AA9&"."&$AB9) -> DefCollateral.AnnexId → DefCollateralAnnex.Id
C10: ProductCode | D10: nvarchar(50) | E10: NOT NULL | G10: UQ1 | H10: RevisionNo | I10: int | J10: NOT NULL | R10: CurrencyCode | S10: nvarchar(3) | T10: NOT NULL | W10: AggregateId | X10: bigint | Y10: NOT NULL | AA10: DefCollateral | AB10: Id | AC10: DefCollateralEligibleCurrency | AD10: DefinitionId | AE10: 1:N · Cash için en az 1 aktif satır | AF10: R04 | AG10: =IF($AF10="POLY",$AC10&".["&$AD10&"] → polymorphic (fiziksel FK yok)",$AC10&"."&$AD10&" → "&$AA10&"."&$AB10) -> DefCollateralEligibleCurrency.DefinitionId → DefCollateral.Id
C11: SubProductCode | D11: nvarchar(50) | E11: NOT NULL | H11: AnnexName | I11: nvarchar(200) | J11: NOT NULL | R11: CurrentBalanceBefore | S11: decimal(38,10) | T11: NOT NULL | W11: EventType | X11: nvarchar(40) | Y11: NOT NULL | AA11: DefCollateral | AB11: Id | AC11: DefCollateralCashTerms | AD11: DefinitionId | AE11: 1:0..1 · yalnız CASH | AF11: R05 | AG11: =IF($AF11="POLY",$AC11&".["&$AD11&"] → polymorphic (fiziksel FK yok)",$AC11&"."&$AD11&" → "&$AA11&"."&$AB11) -> DefCollateralCashTerms.DefinitionId → DefCollateral.Id
C12: MarginType | D12: nvarchar(15) | E12: NOT NULL | H12: CustomerId | I12: int | J12: NOT NULL | R12: ValuationCurrencyCode | S12: nvarchar(3) | T12: NOT NULL | W12: ActorUser | X12: nvarchar(80) | Y12: NULL | AA12: DefCollateral | AB12: Id | AC12: DefCollateralSecurityRule | AD12: DefinitionId | AE12: 1:N · Security Scope = Rule | AF12: R06 | AG12: =IF($AF12="POLY",$AC12&".["&$AD12&"] → polymorphic (fiziksel FK yok)",$AC12&"."&$AD12&" → "&$AA12&"."&$AB12) -> DefCollateralSecurityRule.DefinitionId → DefCollateral.Id
C13: IsIncluded | D13: bit | E13: NOT NULL | H13: IsEnabled | I13: bit | J13: NOT NULL | R13: IsFxConversionRequired | S13: bit | T13: NOT NULL | W13: OccurredDate | X13: datetime | Y13: NOT NULL | AA13: DefCollateral | AB13: Id | AC13: DefCollateralSecurityISIN | AD13: DefinitionId | AE13: 1:N · Security Scope = Specific ISIN | AF13: R07 | AG13: =IF($AF13="POLY",$AC13&".["&$AD13&"] → polymorphic (fiziksel FK yok)",$AC13&"."&$AD13&" → "&$AA13&"."&$AB13) -> DefCollateralSecurityISIN.DefinitionId → DefCollateral.Id
H14: MasterAgreementText | I14: nvarchar(500) | J14: NOT NULL | R14: FxRate | S14: decimal(38,10) | T14: NOT NULL | W14: BeforeData | X14: nvarchar(MAX) | Y14: NULL | AA14: DefCollateral | AB14: Id | AC14: DefCollateralSecurityTerms | AD14: DefinitionId | AE14: 1:0..1 · yalnız SECURITY | AF14: R08 | AG14: =IF($AF14="POLY",$AC14&".["&$AD14&"] → polymorphic (fiziksel FK yok)",$AC14&"."&$AD14&" → "&$AA14&"."&$AB14) -> DefCollateralSecurityTerms.DefinitionId → DefCollateral.Id
H15: CollateralDocumentText | I15: nvarchar(500) | J15: NOT NULL | R15: FxAdjustmentRate | S15: decimal(18,10) | T15: NOT NULL | W15: AfterData | X15: nvarchar(MAX) | Y15: NULL | AA15: DefCollateral | AB15: Id | AC15: DefCollateralSettlementMap | AD15: DefinitionId | AE15: 1:N | AF15: R09 | AG15: =IF($AF15="POLY",$AC15&".["&$AD15&"] → polymorphic (fiziksel FK yok)",$AC15&"."&$AD15&" → "&$AA15&"."&$AB15) -> DefCollateralSettlementMap.DefinitionId → DefCollateral.Id
H16: BaseCurrencyCode | I16: nvarchar(3) | J16: NOT NULL | R16: TransactionValue | S16: decimal(38,10) | T16: NOT NULL | W16: CorrelationId | X16: nvarchar(80) | Y16: NULL | AA16: DefCollateral | AB16: Id | AC16: TxnCollateral | AD16: DefinitionId | AE16: 1:N · 🔴 işlem varken definition silinemez | AF16: R10 | AG16: =IF($AF16="POLY",$AC16&".["&$AD16&"] → polymorphic (fiziksel FK yok)",$AC16&"."&$AD16&" → "&$AA16&"."&$AB16) -> TxnCollateral.DefinitionId → DefCollateral.Id
H17: Direction | I17: nvarchar(20) | J17: NOT NULL | R17: AdjustedEligibleValue | S17: decimal(38,10) | T17: NOT NULL | W17: SourceIp | X17: nvarchar(64) | Y17: NULL | AA17: DefCollateralAnnex | AB17: Id | AC17: TxnCollateral | AD17: AnnexId | AE17: 1:N opsiyonel | AF17: R11 | AG17: =IF($AF17="POLY",$AC17&".["&$AD17&"] → polymorphic (fiziksel FK yok)",$AC17&"."&$AD17&" → "&$AA17&"."&$AB17) -> TxnCollateral.AnnexId → DefCollateralAnnex.Id
H18: ValidFrom | I18: date | J18: NOT NULL | W18: Channel | X18: nvarchar(30) | Y18: NULL | AA18: TxnCollateral | AB18: Id | AC18: TxnCollateralCash | AD18: TxnId | AE18: 1:1 alt tip (CASH) | AF18: R14 | AG18: =IF($AF18="POLY",$AC18&".["&$AD18&"] → polymorphic (fiziksel FK yok)",$AC18&"."&$AD18&" → "&$AA18&"."&$AB18) -> TxnCollateralCash.TxnId → TxnCollateral.Id
B19: =DefCollateralAnnexMarginRule!A1 -> DefCollateralAnnexMarginRule | H19: ValidTo | I19: date | J19: NULL | AA19: TxnCollateral | AB19: Id | AC19: TxnCollateralSecurity | AD19: TxnId | AE19: 1:1 alt tip (SECURITY) | AF19: R15 | AG19: =IF($AF19="POLY",$AC19&".["&$AD19&"] → polymorphic (fiziksel FK yok)",$AC19&"."&$AD19&" → "&$AA19&"."&$AB19) -> TxnCollateralSecurity.TxnId → TxnCollateral.Id
B20: Anahtar | C20: ="Kolon / FK hedefi ("&ROWS(_xlfn.ANCHORARRAY(B21))&")" -> Kolon / FK hedefi (8) | D20: Tip | E20: Null | H20: DisputeToleranceAmount | I20: decimal(38,10) | J20: NOT NULL | AA20: TxnCollateral | AB20: Id | AC20: TxnCollateralValuation | AD20: TxnId | AE20: 1:N · immutable | AF20: R16 | AG20: =IF($AF20="POLY",$AC20&".["&$AD20&"] → polymorphic (fiziksel FK yok)",$AC20&"."&$AD20&" → "&$AA20&"."&$AB20) -> TxnCollateralValuation.TxnId → TxnCollateral.Id
B21: {=_xlfn.LET(_xlpm.d,DefCollateralAnnexMarginRule!$A$7:$F$79,_xlpm.n,INDEX(_xlpm.d,,1),_xlpm.t,INDEX(_xlpm.d,,2),_xlpm.nl,INDEX(_xlpm.d,,3),_xlpm.c,INDEX(_xlpm.d,,5),_xlpm.f,INDEX(_xlpm.d,,6),_xlpm.pk,ISNUMBER(SEARCH("PK_",_xlpm.c))+ISNUMBER(SEARCH("(PK ile)",_xlpm.c)),_xlpm.fk,(LEFT(_xlpm.f,3)="Def")+(LEFT(_xlpm.f,3)="Txn"),_xlpm.qone,ISNUMBER(SEARCH("UQ1",_xlpm.c)),_xlpm.qtwo,ISNUMBER(SEARCH("UQ2",_xlpm.c)),_xlpm.qthree,ISNUMBER(SEARCH("UQ3",_xlpm.c)),_xlpm.uq,ISNUMBER(SEARCH("UQ",_xlpm.c)),_xlpm.ul,IF(_xlpm.qone,"UQ1",IF(_xlpm.qtwo,"UQ2",IF(_xlpm.qthree,"UQ3","UQ"))),_xlpm.ky,TRIM(IF(_xlpm.pk,"PK ","")&IF(_xlpm.fk,"FK ","")&IF(_xlpm.uq*(_xlpm.pk=0),_xlpm.ul,"")),_xlfn._xlws.FILTER(CHOOSE({1,2,3,4},_xlpm.ky,IF(_xlpm.fk,_xlpm.n&" → "&_xlpm.f,_xlpm.n),_xlpm.t,IF(_xlpm.nl="Yes","NULL","NOT NULL")),(_xlpm.n<>"")*(LEFT(_xlpm.n,1)<>"—")))} -> PK | C21: Id | D21: bigint | E21: NOT NULL | H21: DisputeToleranceCurrencyCode | I21: nvarchar(3) | J21: NOT NULL | AA21: TxnCollateral | AB21: Id | AC21: TxnCollateralLimit | AD21: TxnId | AE21: 1:N · ENTRY/VERIFY | AF21: R17 | AG21: =IF($AF21="POLY",$AC21&".["&$AD21&"] → polymorphic (fiziksel FK yok)",$AC21&"."&$AD21&" → "&$AA21&"."&$AB21) -> TxnCollateralLimit.TxnId → TxnCollateral.Id
B22: FK UQ1 | C22: ProductScopeId → DefCollateralAnnexProductScope.Id | D22: bigint | E22: NOT NULL | H22: StateId | I22: int | J22: NOT NULL | AA22: TxnCollateral | AB22: Id | AC22: TxnCollateralPaymentInstruction | AD22: TxnId | AE22: 1:N (sürümlü), aktif sürüm 1 tane | AF22: R18 | AG22: =IF($AF22="POLY",$AC22&".["&$AD22&"] → polymorphic (fiziksel FK yok)",$AC22&"."&$AD22&" → "&$AA22&"."&$AB22) -> TxnCollateralPaymentInstruction.TxnId → TxnCollateral.Id
B23: UQ1 | C23: Party | D23: nvarchar(20) | E23: NOT NULL | H23: StateMaker | I23: nvarchar(80) | J23: NOT NULL | Q23: =TxnCollateralSecurity!A1 -> TxnCollateralSecurity | AA23: TxnCollateral | AB23: Id | AC23: TxnCollateralMessage | AD23: TxnId | AE23: 1:N · idempotent | AF23: R19 | AG23: =IF($AF23="POLY",$AC23&".["&$AD23&"] → polymorphic (fiziksel FK yok)",$AC23&"."&$AD23&" → "&$AA23&"."&$AB23) -> TxnCollateralMessage.TxnId → TxnCollateral.Id
B24: UQ1 | C24: CurrencyCode | D24: nvarchar(3) | E24: NOT NULL | H24: StateDate | I24: datetime | J24: NOT NULL | Q24: Anahtar | R24: ="Kolon / FK hedefi ("&ROWS(_xlfn.ANCHORARRAY(Q25))&")" -> Kolon / FK hedefi (13) | S24: Tip | T24: Null | AA24: TxnCollateralMessage | AB24: Id | AC24: TxnCollateralMessageEvent | AD24: MessageId | AE24: 1:N · append-only | AF24: R20 | AG24: =IF($AF24="POLY",$AC24&".["&$AD24&"] → polymorphic (fiziksel FK yok)",$AC24&"."&$AD24&" → "&$AA24&"."&$AB24) -> TxnCollateralMessageEvent.MessageId → TxnCollateralMessage.Id
C25: ThresholdAmount | D25: decimal(38,10) | E25: NOT NULL | H25: CreatedBy | I25: nvarchar(80) | J25: NOT NULL | Q25: {=_xlfn.LET(_xlpm.d,TxnCollateralSecurity!$A$7:$F$80,_xlpm.n,INDEX(_xlpm.d,,1),_xlpm.t,INDEX(_xlpm.d,,2),_xlpm.nl,INDEX(_xlpm.d,,3),_xlpm.c,INDEX(_xlpm.d,,5),_xlpm.f,INDEX(_xlpm.d,,6),_xlpm.pk,ISNUMBER(SEARCH("PK_",_xlpm.c))+ISNUMBER(SEARCH("(PK ile)",_xlpm.c)),_xlpm.fk,(LEFT(_xlpm.f,3)="Def")+(LEFT(_xlpm.f,3)="Txn"),_xlpm.qone,ISNUMBER(SEARCH("UQ1",_xlpm.c)),_xlpm.qtwo,ISNUMBER(SEARCH("UQ2",_xlpm.c)),_xlpm.qthree,ISNUMBER(SEARCH("UQ3",_xlpm.c)),_xlpm.uq,ISNUMBER(SEARCH("UQ",_xlpm.c)),_xlpm.ul,IF(_xlpm.qone,"UQ1",IF(_xlpm.qtwo,"UQ2",IF(_xlpm.qthree,"UQ3","UQ"))),_xlpm.ky,TRIM(IF(_xlpm.pk,"PK ","")&IF(_xlpm.fk,"FK ","")&IF(_xlpm.uq*(_xlpm.pk=0),_xlpm.ul,"")),_xlfn._xlws.FILTER(CHOOSE({1,2,3,4},_xlpm.ky,IF(_xlpm.fk,_xlpm.n&" → "&_xlpm.f,_xlpm.n),_xlpm.t,IF(_xlpm.nl="Yes","NULL","NOT NULL")),(_xlpm.n<>"")*(LEFT(_xlpm.n,1)<>"—")))} -> PK FK | R25: TxnId → TxnCollateral.Id | S25: bigint | T25: NOT NULL | AA25: TxnCollateral | AB25: Id | AC25: TxnCollateral | AD25: ReversalOfId | AE25: 1:0..1 self | AF25: SELF | AG25: =IF($AF25="POLY",$AC25&".["&$AD25&"] → polymorphic (fiziksel FK yok)",$AC25&"."&$AD25&" → "&$AA25&"."&$AB25) -> TxnCollateral.ReversalOfId → TxnCollateral.Id
C26: MtaAmount | D26: decimal(38,10) | E26: NOT NULL | H26: CreatedDate | I26: datetime | J26: NOT NULL | R26: ISIN | S26: nvarchar(12) | T26: NOT NULL | AA26: DefCollateral | AB26: Id | AC26: TxnCollateralPosition | AD26: DefinitionId | AE26: 1:N · bakiye projeksiyonu | AF26: R12 | AG26: =IF($AF26="POLY",$AC26&".["&$AD26&"] → polymorphic (fiziksel FK yok)",$AC26&"."&$AD26&" → "&$AA26&"."&$AB26) -> TxnCollateralPosition.DefinitionId → DefCollateral.Id
C27: RoundingAmount | D27: decimal(38,10) | E27: NOT NULL | R27: Nominal | S27: decimal(38,10) | T27: NOT NULL | AA27: TxnCollateral | AB27: Id | AC27: TxnCollateralPosition | AD27: LastTxnId | AE27: 1:0..1 · son işleme opsiyonel referans | AF27: R13 | AG27: =IF($AF27="POLY",$AC27&".["&$AD27&"] → polymorphic (fiziksel FK yok)",$AC27&"."&$AD27&" → "&$AA27&"."&$AB27) -> TxnCollateralPosition.LastTxnId → TxnCollateral.Id
C28: RoundingMethod | D28: nvarchar(12) | E28: NOT NULL | R28: CurrentNominalBefore | S28: decimal(38,10) | T28: NOT NULL | AA28: (polymorphic) | AB28: — | AC28: CollateralAuditLog | AD28: AggregateId + AggregateType | AE28: Polymorphic — gerçek FK constraint mümkün değil | AF28: POLY | AG28: =IF($AF28="POLY",$AC28&".["&$AD28&"] → polymorphic (fiziksel FK yok)",$AC28&"."&$AD28&" → "&$AA28&"."&$AB28) -> CollateralAuditLog.[AggregateId + AggregateType] → polymorphic (fiziksel FK yok)
R29: Price | S29: decimal(38,10) | T29: NOT NULL | AA29: B) Dış bağımlılıklar — mevcut MM tabloları vs yeni gerekenler | AB29: 0 | AC29: 0 | AD29: 0 | AE29: 0
R30: PriceDate | S30: date | T30: NOT NULL | AA30: Kolon(lar) | AB30: Hedef | AC30: Durum | AD30: Not | AE30: 0
R31: PriceFactor | S31: decimal(18,10) | T31: NOT NULL | AA31: CustomerId (4 tabloda) | AB31: CusCustomer.Id | AC31: ✅ MM'de VAR | AD31: Counterparty = MM'in Customer kavramı. Tip: int (MM'in mevcut tipi) | AE31: 0
G32: =DefCollateral!A1 -> DefCollateral | L32: =TxnCollateral!A1 -> TxnCollateral | R32: MarketValue | S32: decimal(38,10) | T32: NOT NULL | AA32: CurrencyCode (çok sayıda) | AB32: Currency | AC32: ✅ MM'de VAR | AD32: nvarchar(3) doğal anahtar | AE32: 0
G33: Anahtar | H33: ="Kolon / FK hedefi ("&ROWS(_xlfn.ANCHORARRAY(G34))&")" -> Kolon / FK hedefi (17) | I33: Tip | J33: Null | L33: Anahtar | M33: ="Kolon / FK hedefi ("&ROWS(_xlfn.ANCHORARRAY(L34))&")" -> Kolon / FK hedefi (30) | N33: Tip | O33: Null | R33: ValuationCurrencyCode | S33: nvarchar(3) | T33: NOT NULL | AA33: PortfolioId | AB33: PrfPortfolio.Id | AC33: ✅ MM'de VAR | AD33: 🔑 Varsayılan portföy parametreden PATH ile çözülür, Code ile değil | AE33: 0
B34: =DefCollateralEligibleCurrency!A1 -> DefCollateralEligibleCurrency | G34: {=_xlfn.LET(_xlpm.d,DefCollateral!$A$7:$F$80,_xlpm.n,INDEX(_xlpm.d,,1),_xlpm.t,INDEX(_xlpm.d,,2),_xlpm.nl,INDEX(_xlpm.d,,3),_xlpm.c,INDEX(_xlpm.d,,5),_xlpm.f,INDEX(_xlpm.d,,6),_xlpm.pk,ISNUMBER(SEARCH("PK_",_xlpm.c))+ISNUMBER(SEARCH("(PK ile)",_xlpm.c)),_xlpm.fk,(LEFT(_xlpm.f,3)="Def")+(LEFT(_xlpm.f,3)="Txn"),_xlpm.qone,ISNUMBER(SEARCH("UQ1",_xlpm.c)),_xlpm.qtwo,ISNUMBER(SEARCH("UQ2",_xlpm.c)),_xlpm.qthree,ISNUMBER(SEARCH("UQ3",_xlpm.c)),_xlpm.uq,ISNUMBER(SEARCH("UQ",_xlpm.c)),_xlpm.ul,IF(_xlpm.qone,"UQ1",IF(_xlpm.qtwo,"UQ2",IF(_xlpm.qthree,"UQ3","UQ"))),_xlpm.ky,TRIM(IF(_xlpm.pk,"PK ","")&IF(_xlpm.fk,"FK ","")&IF(_xlpm.uq*(_xlpm.pk=0),_xlpm.ul,"")),_xlfn._xlws.FILTER(CHOOSE({1,2,3,4},_xlpm.ky,IF(_xlpm.fk,_xlpm.n&" → "&_xlpm.f,_xlpm.n),_xlpm.t,IF(_xlpm.nl="Yes","NULL","NOT NULL")),(_xlpm.n<>"")*(LEFT(_xlpm.n,1)<>"—")))} -> PK | H34: Id | I34: bigint | J34: NOT NULL | L34: {=_xlfn.LET(_xlpm.d,TxnCollateral!$A$7:$F$79,_xlpm.n,INDEX(_xlpm.d,,1),_xlpm.t,INDEX(_xlpm.d,,2),_xlpm.nl,INDEX(_xlpm.d,,3),_xlpm.c,INDEX(_xlpm.d,,5),_xlpm.f,INDEX(_xlpm.d,,6),_xlpm.pk,ISNUMBER(SEARCH("PK_",_xlpm.c))+ISNUMBER(SEARCH("(PK ile)",_xlpm.c)),_xlpm.fk,(LEFT(_xlpm.f,3)="Def")+(LEFT(_xlpm.f,3)="Txn"),_xlpm.qone,ISNUMBER(SEARCH("UQ1",_xlpm.c)),_xlpm.qtwo,ISNUMBER(SEARCH("UQ2",_xlpm.c)),_xlpm.qthree,ISNUMBER(SEARCH("UQ3",_xlpm.c)),_xlpm.uq,ISNUMBER(SEARCH("UQ",_xlpm.c)),_xlpm.ul,IF(_xlpm.qone,"UQ1",IF(_xlpm.qtwo,"UQ2",IF(_xlpm.qthree,"UQ3","UQ"))),_xlpm.ky,TRIM(IF(_xlpm.pk,"PK ","")&IF(_xlpm.fk,"FK ","")&IF(_xlpm.uq*(_xlpm.pk=0),_xlpm.ul,"")),_xlfn._xlws.FILTER(CHOOSE({1,2,3,4},_xlpm.ky,IF(_xlpm.fk,_xlpm.n&" → "&_xlpm.f,_xlpm.n),_xlpm.t,IF(_xlpm.nl="Yes","NULL","NOT NULL")),(_xlpm.n<>"")*(LEFT(_xlpm.n,1)<>"—")))} -> PK | M34: Id | N34: bigint | O34: NOT NULL | R34: AssetHaircutRate | S34: decimal(18,10) | T34: NOT NULL | AA34: SettlementTypeId | AB34: SettlementType.Id | AC34: ✅ MM'de VAR | AD34: Değer kümesi örtüşüyor (Gross/Netting) — yeni tablo AÇMA | AE34: 0
B35: Anahtar | C35: ="Kolon / FK hedefi ("&ROWS(_xlfn.ANCHORARRAY(B36))&")" -> Kolon / FK hedefi (4) | D35: Tip | E35: Null | G35: UQ1 | H35: CollateralCode | I35: nvarchar(50) | J35: NOT NULL | L35: UQ1 | M35: LogicalReference | N35: nvarchar(80) | O35: NOT NULL | R35: FxHaircutRate | S35: decimal(18,10) | T35: NOT NULL | AA35: PaymentInstructionTypeId | AB35: PaymentInstructionType.Id | AC35: ✅ MM'de VAR | AD35: B2B/A2A/Vostro/A2AD — yeni tablo AÇMA | AE35: 0
B36: {=_xlfn.LET(_xlpm.d,DefCollateralEligibleCurrency!$A$7:$F$79,_xlpm.n,INDEX(_xlpm.d,,1),_xlpm.t,INDEX(_xlpm.d,,2),_xlpm.nl,INDEX(_xlpm.d,,3),_xlpm.c,INDEX(_xlpm.d,,5),_xlpm.f,INDEX(_xlpm.d,,6),_xlpm.pk,ISNUMBER(SEARCH("PK_",_xlpm.c))+ISNUMBER(SEARCH("(PK ile)",_xlpm.c)),_xlpm.fk,(LEFT(_xlpm.f,3)="Def")+(LEFT(_xlpm.f,3)="Txn"),_xlpm.qone,ISNUMBER(SEARCH("UQ1",_xlpm.c)),_xlpm.qtwo,ISNUMBER(SEARCH("UQ2",_xlpm.c)),_xlpm.qthree,ISNUMBER(SEARCH("UQ3",_xlpm.c)),_xlpm.uq,ISNUMBER(SEARCH("UQ",_xlpm.c)),_xlpm.ul,IF(_xlpm.qone,"UQ1",IF(_xlpm.qtwo,"UQ2",IF(_xlpm.qthree,"UQ3","UQ"))),_xlpm.ky,TRIM(IF(_xlpm.pk,"PK ","")&IF(_xlpm.fk,"FK ","")&IF(_xlpm.uq*(_xlpm.pk=0),_xlpm.ul,"")),_xlfn._xlws.FILTER(CHOOSE({1,2,3,4},_xlpm.ky,IF(_xlpm.fk,_xlpm.n&" → "&_xlpm.f,_xlpm.n),_xlpm.t,IF(_xlpm.nl="Yes","NULL","NOT NULL")),(_xlpm.n<>"")*(LEFT(_xlpm.n,1)<>"—")))} -> PK FK | C36: DefinitionId → DefCollateral.Id | D36: bigint | E36: NOT NULL | G36: UQ1 | H36: RevisionNo | I36: int | J36: NOT NULL | L36: UQ2 | M36: TransactionReference | N36: nvarchar(60) | O36: NOT NULL | R36: FxRate | S36: decimal(38,10) | T36: NOT NULL | AA36: TraderUserId / StateMaker / CreatedBy | AB36: Kullanıcı (nvarchar(80)) | AC36: ✅ MM deseni | AD36: MM ayrı User tablosuna FK vermiyor, string tutuyor | AE36: 0
B37: PK | C37: CurrencyCode | D37: nvarchar(3) | E37: NOT NULL | H37: CollateralName | I37: nvarchar(200) | J37: NOT NULL | L37: FK | M37: DefinitionId → DefCollateral.Id | N37: bigint | O37: NOT NULL | R37: AdjustedEligibleValue | S37: decimal(38,10) | T37: NOT NULL | AA37: ProductCode, SubProductCode | AB37: Ürün kataloğu | AC37: ⚠️ NETLEŞMEDİ | AD37: MM'in PrdProductDefinition'ı hazine ürün ailesi (FX/IR/Repo) için yeterli mi? | AE37: 0
C38: FxAdjustmentRate | D38: decimal(18,10) | E38: NOT NULL | G38: FK | H38: AnnexId → DefCollateralAnnex.Id | I38: bigint | J38: NULL | L38: FK | M38: AnnexId → DefCollateralAnnex.Id | N38: bigint | O38: NULL | AA38: SettlementAccountId, InterestAccountId | AB38: Hesap master | AC38: ⚠️ NETLEŞMEDİ | AD38: MM'de hesap Fimple'dan geliyor (AccountNumber/GLCode kolonları), ayrı master yok | AE38: 0
C39: IsActive | D39: bit | E39: NOT NULL | H39: CustomerId | I39: int | J39: NOT NULL | M39: CustomerId | N39: int | O39: NOT NULL | AA39: SsiId (5 kolonda) | AB39: SSI master | AC39: 🔴 YENİ GEREKLİ | AD39: MM'de yok. Collateral içinde mi, ortak modülde mi? | AE39: 0
H40: CollateralType | I40: nvarchar(12) | J40: NOT NULL | M40: PortfolioId | N40: int | O40: NOT NULL | AA40: ISIN, SecurityTypeCode, IssuerTypeCode, MinimumRatingCode | AB40: Menkul kıymet master | AC40: 🔴 YENİ GEREKLİ | AD40: Collateral'ın en büyük dış bağımlılığı | AE40: 0
H41: IsEnabled | I41: bit | J41: NOT NULL | L41: UQ3 | M41: SourceSystem | N41: nvarchar(50) | O41: NULL | AA41: SettlementLocationCode | AB41: CSD/ICSD kataloğu | AC41: 🔴 YENİ GEREKLİ | AD41: Takasbank/Euroclear/Clearstream | AE41: 0
H42: EligibilityDirection | I42: nvarchar(20) | J42: NOT NULL | L42: UQ3 | M42: ExternalReference | N42: nvarchar(100) | O42: NULL | AA42: PaymentRouteCode | AB42: Ödeme rota konfigürasyonu | AC42: 🔴 YENİ GEREKLİ | AD42: pacs.009 / MT202 / local route seçimi | AE42: 0
H43: ValuationCurrencyCode | I43: nvarchar(3) | J43: NOT NULL | M43: TradeDate | N43: date | O43: NOT NULL | Q43: =TxnCollateralValuation!A1 -> TxnCollateralValuation | AA43: ReferenceRateCode | AB43: Referans oran kataloğu | AC43: 🔴 YENİ GEREKLİ | AD43: €STR/SOFR/SONIA/TLREF | AE43: 0
H44: ValidFrom | I44: date | J44: NOT NULL | M44: ValueDate | N44: date | O44: NOT NULL | Q44: Anahtar | R44: ="Kolon / FK hedefi ("&ROWS(_xlfn.ANCHORARRAY(Q45))&")" -> Kolon / FK hedefi (15) | S44: Tip | T44: Null | AA44: CountryOfRiskCode | AB44: Ülke kataloğu | AC44: ⚠️ MM'de DefCountry var | AD44: Kontrol edilmeli | AE44: 0
B45: =DefCollateralCashTerms!A1 -> DefCollateralCashTerms | H45: ValidTo | I45: date | J45: NULL | M45: InputDate | N45: datetime | O45: NOT NULL | Q45: {=_xlfn.LET(_xlpm.d,TxnCollateralValuation!$A$7:$F$80,_xlpm.n,INDEX(_xlpm.d,,1),_xlpm.t,INDEX(_xlpm.d,,2),_xlpm.nl,INDEX(_xlpm.d,,3),_xlpm.c,INDEX(_xlpm.d,,5),_xlpm.f,INDEX(_xlpm.d,,6),_xlpm.pk,ISNUMBER(SEARCH("PK_",_xlpm.c))+ISNUMBER(SEARCH("(PK ile)",_xlpm.c)),_xlpm.fk,(LEFT(_xlpm.f,3)="Def")+(LEFT(_xlpm.f,3)="Txn"),_xlpm.qone,ISNUMBER(SEARCH("UQ1",_xlpm.c)),_xlpm.qtwo,ISNUMBER(SEARCH("UQ2",_xlpm.c)),_xlpm.qthree,ISNUMBER(SEARCH("UQ3",_xlpm.c)),_xlpm.uq,ISNUMBER(SEARCH("UQ",_xlpm.c)),_xlpm.ul,IF(_xlpm.qone,"UQ1",IF(_xlpm.qtwo,"UQ2",IF(_xlpm.qthree,"UQ3","UQ"))),_xlpm.ky,TRIM(IF(_xlpm.pk,"PK ","")&IF(_xlpm.fk,"FK ","")&IF(_xlpm.uq*(_xlpm.pk=0),_xlpm.ul,"")),_xlfn._xlws.FILTER(CHOOSE({1,2,3,4},_xlpm.ky,IF(_xlpm.fk,_xlpm.n&" → "&_xlpm.f,_xlpm.n),_xlpm.t,IF(_xlpm.nl="Yes","NULL","NOT NULL")),(_xlpm.n<>"")*(LEFT(_xlpm.n,1)<>"—")))} -> PK | R45: Id | S45: bigint | T45: NOT NULL
B46: Anahtar | C46: ="Kolon / FK hedefi ("&ROWS(_xlfn.ANCHORARRAY(B47))&")" -> Kolon / FK hedefi (10) | D46: Tip | E46: Null | H46: StateId | I46: int | J46: NOT NULL | M46: TransactionType | N46: nvarchar(12) | O46: NOT NULL | Q46: FK | R46: TxnId → TxnCollateral.Id | S46: bigint | T46: NOT NULL
B47: {=_xlfn.LET(_xlpm.d,DefCollateralCashTerms!$A$7:$F$80,_xlpm.n,INDEX(_xlpm.d,,1),_xlpm.t,INDEX(_xlpm.d,,2),_xlpm.nl,INDEX(_xlpm.d,,3),_xlpm.c,INDEX(_xlpm.d,,5),_xlpm.f,INDEX(_xlpm.d,,6),_xlpm.pk,ISNUMBER(SEARCH("PK_",_xlpm.c))+ISNUMBER(SEARCH("(PK ile)",_xlpm.c)),_xlpm.fk,(LEFT(_xlpm.f,3)="Def")+(LEFT(_xlpm.f,3)="Txn"),_xlpm.qone,ISNUMBER(SEARCH("UQ1",_xlpm.c)),_xlpm.qtwo,ISNUMBER(SEARCH("UQ2",_xlpm.c)),_xlpm.qthree,ISNUMBER(SEARCH("UQ3",_xlpm.c)),_xlpm.uq,ISNUMBER(SEARCH("UQ",_xlpm.c)),_xlpm.ul,IF(_xlpm.qone,"UQ1",IF(_xlpm.qtwo,"UQ2",IF(_xlpm.qthree,"UQ3","UQ"))),_xlpm.ky,TRIM(IF(_xlpm.pk,"PK ","")&IF(_xlpm.fk,"FK ","")&IF(_xlpm.uq*(_xlpm.pk=0),_xlpm.ul,"")),_xlfn._xlws.FILTER(CHOOSE({1,2,3,4},_xlpm.ky,IF(_xlpm.fk,_xlpm.n&" → "&_xlpm.f,_xlpm.n),_xlpm.t,IF(_xlpm.nl="Yes","NULL","NOT NULL")),(_xlpm.n<>"")*(LEFT(_xlpm.n,1)<>"—")))} -> PK FK | C47: DefinitionId → DefCollateral.Id | D47: bigint | E47: NOT NULL | H47: StateMaker | I47: nvarchar(80) | J47: NOT NULL | M47: MarginType | N47: nvarchar(15) | O47: NOT NULL | R47: SnapshotStage | S47: nvarchar(20) | T47: NOT NULL
C48: RateType | D48: nvarchar(20) | E48: NULL | H48: StateDate | I48: datetime | J48: NOT NULL | M48: CollateralType | N48: nvarchar(12) | O48: NOT NULL | R48: FxRate | S48: decimal(38,10) | T48: NULL
C49: ReferenceRateCode | D49: nvarchar(30) | E49: NULL | H49: CreatedBy | I49: nvarchar(80) | J49: NOT NULL | M49: LifecycleStatus | N49: nvarchar(30) | O49: NOT NULL | R49: RateConvention | S49: nvarchar(30) | T49: NULL
C50: SpreadBps | D50: decimal(18,10) | E50: NULL | H50: CreatedDate | I50: datetime | J50: NOT NULL | M50: EconomicVersion | N50: int | O50: NOT NULL | R50: Price | S50: decimal(38,10) | T50: NULL
C51: FixedRate | D51: decimal(18,10) | E51: NULL | L51: FK | M51: ReversalOfId → TxnCollateral.Id (self) | N51: bigint | O51: NULL | R51: PriceDate | S51: date | T51: NULL
C52: CompoundingMethod | D52: nvarchar(25) | E52: NULL | M52: Trader | N52: nvarchar(80) | O52: NOT NULL | R52: AssetHaircutRate | S52: decimal(18,10) | T52: NULL
C53: DayCount | D53: nvarchar(15) | E53: NULL | M53: StateId | N53: bigint | O53: NOT NULL | R53: FxAdjustmentRate | S53: decimal(18,10) | T53: NULL
C54: PaymentFrequency | D54: nvarchar(25) | E54: NULL | M54: StateMaker | N54: nvarchar(80) | O54: NOT NULL | R54: FxHaircutRate | S54: decimal(18,10) | T54: NULL
C55: BusinessDayRule | D55: nvarchar(25) | E55: NULL | M55: StateDate | N55: datetime | O55: NOT NULL | R55: GrossValue | S55: decimal(38,10) | T55: NOT NULL
C56: IsNegativeRateAllowed | D56: bit | E56: NULL | G56: =TxnCollateralPosition!A1 -> TxnCollateralPosition | M56: CreatedBy | N56: nvarchar(80) | O56: NOT NULL | R56: EligibleValue | S56: decimal(38,10) | T56: NOT NULL
G57: Anahtar | H57: ="Kolon / FK hedefi ("&ROWS(_xlfn.ANCHORARRAY(G58))&")" -> Kolon / FK hedefi (7) | I57: Tip | J57: Null | M57: CreatedDate | N57: datetime | O57: NOT NULL | R57: ValuationCurrencyCode | S57: nvarchar(3) | T57: NOT NULL
G58: {=_xlfn.LET(_xlpm.d,TxnCollateralPosition!$A$7:$F$80,_xlpm.n,INDEX(_xlpm.d,,1),_xlpm.t,INDEX(_xlpm.d,,2),_xlpm.nl,INDEX(_xlpm.d,,3),_xlpm.c,INDEX(_xlpm.d,,5),_xlpm.f,INDEX(_xlpm.d,,6),_xlpm.pk,ISNUMBER(SEARCH("PK_",_xlpm.c))+ISNUMBER(SEARCH("(PK ile)",_xlpm.c)),_xlpm.fk,(LEFT(_xlpm.f,3)="Def")+(LEFT(_xlpm.f,3)="Txn"),_xlpm.qone,ISNUMBER(SEARCH("UQ1",_xlpm.c)),_xlpm.qtwo,ISNUMBER(SEARCH("UQ2",_xlpm.c)),_xlpm.qthree,ISNUMBER(SEARCH("UQ3",_xlpm.c)),_xlpm.uq,ISNUMBER(SEARCH("UQ",_xlpm.c)),_xlpm.ul,IF(_xlpm.qone,"UQ1",IF(_xlpm.qtwo,"UQ2",IF(_xlpm.qthree,"UQ3","UQ"))),_xlpm.ky,TRIM(IF(_xlpm.pk,"PK ","")&IF(_xlpm.fk,"FK ","")&IF(_xlpm.uq*(_xlpm.pk=0),_xlpm.ul,"")),_xlfn._xlws.FILTER(CHOOSE({1,2,3,4},_xlpm.ky,IF(_xlpm.fk,_xlpm.n&" → "&_xlpm.f,_xlpm.n),_xlpm.t,IF(_xlpm.nl="Yes","NULL","NOT NULL")),(_xlpm.n<>"")*(LEFT(_xlpm.n,1)<>"—")))} -> PK FK | H58: DefinitionId → DefCollateral.Id | I58: bigint | J58: NOT NULL | M58: PreviousStateId | N58: bigint | O58: NULL | R58: AsOfDate | S58: datetime | T58: NOT NULL
G59: PK | H59: MarginType | I59: nvarchar(15) | J59: NOT NULL | M59: PreviousStateMaker | N59: nvarchar(80) | O59: NULL | R59: SourceRefHash | S59: nvarchar(128) | T59: NULL
G60: PK | H60: AssetCode | I60: nvarchar(12) | J60: NOT NULL | M60: PreviousStateDate | N60: datetime | O60: NULL
H61: CollateralType | I61: nvarchar(12) | J61: NOT NULL | M61: FlowId | N61: bigint | O61: NOT NULL
B62: =DefCollateralSettlementMap!A1 -> DefCollateralSettlementMap | H62: CurrentBalance | I62: decimal(38,10) | J62: NOT NULL | M62: LastActionId | N62: bigint | O62: NOT NULL
B63: Anahtar | C63: ="Kolon / FK hedefi ("&ROWS(_xlfn.ANCHORARRAY(B64))&")" -> Kolon / FK hedefi (9) | D63: Tip | E63: Null | G63: FK | H63: LastTxnId → TxnCollateral.Id | I63: bigint | J63: NULL | M63: PreviousActionId | N63: bigint | O63: NULL
B64: {=_xlfn.LET(_xlpm.d,DefCollateralSettlementMap!$A$7:$F$79,_xlpm.n,INDEX(_xlpm.d,,1),_xlpm.t,INDEX(_xlpm.d,,2),_xlpm.nl,INDEX(_xlpm.d,,3),_xlpm.c,INDEX(_xlpm.d,,5),_xlpm.f,INDEX(_xlpm.d,,6),_xlpm.pk,ISNUMBER(SEARCH("PK_",_xlpm.c))+ISNUMBER(SEARCH("(PK ile)",_xlpm.c)),_xlpm.fk,(LEFT(_xlpm.f,3)="Def")+(LEFT(_xlpm.f,3)="Txn"),_xlpm.qone,ISNUMBER(SEARCH("UQ1",_xlpm.c)),_xlpm.qtwo,ISNUMBER(SEARCH("UQ2",_xlpm.c)),_xlpm.qthree,ISNUMBER(SEARCH("UQ3",_xlpm.c)),_xlpm.uq,ISNUMBER(SEARCH("UQ",_xlpm.c)),_xlpm.ul,IF(_xlpm.qone,"UQ1",IF(_xlpm.qtwo,"UQ2",IF(_xlpm.qthree,"UQ3","UQ"))),_xlpm.ky,TRIM(IF(_xlpm.pk,"PK ","")&IF(_xlpm.fk,"FK ","")&IF(_xlpm.uq*(_xlpm.pk=0),_xlpm.ul,"")),_xlfn._xlws.FILTER(CHOOSE({1,2,3,4},_xlpm.ky,IF(_xlpm.fk,_xlpm.n&" → "&_xlpm.f,_xlpm.n),_xlpm.t,IF(_xlpm.nl="Yes","NULL","NOT NULL")),(_xlpm.n<>"")*(LEFT(_xlpm.n,1)<>"—")))} -> PK | C64: Id | D64: bigint | E64: NOT NULL | H64: AsOfDate | I64: datetime | J64: NOT NULL
B65: FK | C65: DefinitionId → DefCollateral.Id | D65: bigint | E65: NOT NULL | Q65: =TxnCollateralLimit!A1 -> TxnCollateralLimit
C66: TransactionType | D66: nvarchar(12) | E66: NOT NULL | Q66: Anahtar | R66: ="Kolon / FK hedefi ("&ROWS(_xlfn.ANCHORARRAY(Q67))&")" -> Kolon / FK hedefi (18) | S66: Tip | T66: Null
C67: CurrencyCode | D67: nvarchar(3) | E67: NULL | Q67: {=_xlfn.LET(_xlpm.d,TxnCollateralLimit!$A$7:$F$80,_xlpm.n,INDEX(_xlpm.d,,1),_xlpm.t,INDEX(_xlpm.d,,2),_xlpm.nl,INDEX(_xlpm.d,,3),_xlpm.c,INDEX(_xlpm.d,,5),_xlpm.f,INDEX(_xlpm.d,,6),_xlpm.pk,ISNUMBER(SEARCH("PK_",_xlpm.c))+ISNUMBER(SEARCH("(PK ile)",_xlpm.c)),_xlpm.fk,(LEFT(_xlpm.f,3)="Def")+(LEFT(_xlpm.f,3)="Txn"),_xlpm.qone,ISNUMBER(SEARCH("UQ1",_xlpm.c)),_xlpm.qtwo,ISNUMBER(SEARCH("UQ2",_xlpm.c)),_xlpm.qthree,ISNUMBER(SEARCH("UQ3",_xlpm.c)),_xlpm.uq,ISNUMBER(SEARCH("UQ",_xlpm.c)),_xlpm.ul,IF(_xlpm.qone,"UQ1",IF(_xlpm.qtwo,"UQ2",IF(_xlpm.qthree,"UQ3","UQ"))),_xlpm.ky,TRIM(IF(_xlpm.pk,"PK ","")&IF(_xlpm.fk,"FK ","")&IF(_xlpm.uq*(_xlpm.pk=0),_xlpm.ul,"")),_xlfn._xlws.FILTER(CHOOSE({1,2,3,4},_xlpm.ky,IF(_xlpm.fk,_xlpm.n&" → "&_xlpm.f,_xlpm.n),_xlpm.t,IF(_xlpm.nl="Yes","NULL","NOT NULL")),(_xlpm.n<>"")*(LEFT(_xlpm.n,1)<>"—")))} -> PK | R67: Id | S67: bigint | T67: NOT NULL
C68: SettlementLocationCode | D68: nvarchar(40) | E68: NULL | Q68: FK UQ1 | R68: TxnId → TxnCollateral.Id | S68: bigint | T68: NOT NULL
C69: SettlementAccountId | D69: int | E69: NULL | Q69: UQ1 | R69: SnapshotStage | S69: nvarchar(20) | T69: NOT NULL
C70: InterestAccountId | D70: int | E70: NULL | R70: LimitStatus | S70: nvarchar(25) | T70: NOT NULL
C71: SsiId | D71: bigint | E71: NULL | R71: AvailabilityStatus | S71: nvarchar(20) | T71: NOT NULL
C72: PaymentRouteCode | D72: nvarchar(40) | E72: NULL | R72: DecisionCode | S72: nvarchar(40) | T72: NOT NULL
R73: IsBlocking | S73: bit | T73: NOT NULL
R74: CustomerId | S74: int | T74: NOT NULL
R75: CustomerNo | S75: nvarchar(50) | T75: NOT NULL
R76: LimitCurrencyCode | S76: nvarchar(3) | T76: NOT NULL
R77: CountryLimit | S77: decimal(38,10) | T77: NOT NULL
B78: =DefCollateralSecurityRule!A1 -> DefCollateralSecurityRule | R78: TotalLimit | S78: decimal(38,10) | T78: NOT NULL
B79: Anahtar | C79: ="Kolon / FK hedefi ("&ROWS(_xlfn.ANCHORARRAY(B80))&")" -> Kolon / FK hedefi (9) | D79: Tip | E79: Null | R79: UsedLimit | S79: decimal(38,10) | T79: NOT NULL
B80: {=_xlfn.LET(_xlpm.d,DefCollateralSecurityRule!$A$7:$F$79,_xlpm.n,INDEX(_xlpm.d,,1),_xlpm.t,INDEX(_xlpm.d,,2),_xlpm.nl,INDEX(_xlpm.d,,3),_xlpm.c,INDEX(_xlpm.d,,5),_xlpm.f,INDEX(_xlpm.d,,6),_xlpm.pk,ISNUMBER(SEARCH("PK_",_xlpm.c))+ISNUMBER(SEARCH("(PK ile)",_xlpm.c)),_xlpm.fk,(LEFT(_xlpm.f,3)="Def")+(LEFT(_xlpm.f,3)="Txn"),_xlpm.qone,ISNUMBER(SEARCH("UQ1",_xlpm.c)),_xlpm.qtwo,ISNUMBER(SEARCH("UQ2",_xlpm.c)),_xlpm.qthree,ISNUMBER(SEARCH("UQ3",_xlpm.c)),_xlpm.uq,ISNUMBER(SEARCH("UQ",_xlpm.c)),_xlpm.ul,IF(_xlpm.qone,"UQ1",IF(_xlpm.qtwo,"UQ2",IF(_xlpm.qthree,"UQ3","UQ"))),_xlpm.ky,TRIM(IF(_xlpm.pk,"PK ","")&IF(_xlpm.fk,"FK ","")&IF(_xlpm.uq*(_xlpm.pk=0),_xlpm.ul,"")),_xlfn._xlws.FILTER(CHOOSE({1,2,3,4},_xlpm.ky,IF(_xlpm.fk,_xlpm.n&" → "&_xlpm.f,_xlpm.n),_xlpm.t,IF(_xlpm.nl="Yes","NULL","NOT NULL")),(_xlpm.n<>"")*(LEFT(_xlpm.n,1)<>"—")))} -> PK | C80: Id | D80: bigint | E80: NOT NULL | R80: AvailableLimit | S80: decimal(38,10) | T80: NOT NULL
B81: FK | C81: DefinitionId → DefCollateral.Id | D81: bigint | E81: NOT NULL | R81: UtilizationRate | S81: decimal(18,10) | T81: NOT NULL
C82: SecurityTypeCode | D82: nvarchar(40) | E82: NOT NULL | R82: RiskAmount | S82: decimal(38,10) | T82: NOT NULL
C83: IssuerTypeCode | D83: nvarchar(40) | E83: NOT NULL | R83: AsOfDate | S83: datetime | T83: NOT NULL
C84: CountryOfRiskCode | D84: nvarchar(3) | E84: NULL | R84: SourceRefHash | S84: nvarchar(128) | T84: NULL
C85: EligibleCurrencyCode | D85: nvarchar(3) | E85: NOT NULL
C86: MinimumRatingCode | D86: nvarchar(30) | E86: NULL
C87: MaxRemainingMaturityDays | D87: int | E87: NULL
C88: IsActive | D88: bit | E88: NOT NULL
Q90: =TxnCollateralPaymentInstruction!A1 -> TxnCollateralPaymentInstruction
Q91: Anahtar | R91: ="Kolon / FK hedefi ("&ROWS(_xlfn.ANCHORARRAY(Q92))&")" -> Kolon / FK hedefi (15) | S91: Tip | T91: Null
Q92: {=_xlfn.LET(_xlpm.d,TxnCollateralPaymentInstruction!$A$7:$F$79,_xlpm.n,INDEX(_xlpm.d,,1),_xlpm.t,INDEX(_xlpm.d,,2),_xlpm.nl,INDEX(_xlpm.d,,3),_xlpm.c,INDEX(_xlpm.d,,5),_xlpm.f,INDEX(_xlpm.d,,6),_xlpm.pk,ISNUMBER(SEARCH("PK_",_xlpm.c))+ISNUMBER(SEARCH("(PK ile)",_xlpm.c)),_xlpm.fk,(LEFT(_xlpm.f,3)="Def")+(LEFT(_xlpm.f,3)="Txn"),_xlpm.qone,ISNUMBER(SEARCH("UQ1",_xlpm.c)),_xlpm.qtwo,ISNUMBER(SEARCH("UQ2",_xlpm.c)),_xlpm.qthree,ISNUMBER(SEARCH("UQ3",_xlpm.c)),_xlpm.uq,ISNUMBER(SEARCH("UQ",_xlpm.c)),_xlpm.ul,IF(_xlpm.qone,"UQ1",IF(_xlpm.qtwo,"UQ2",IF(_xlpm.qthree,"UQ3","UQ"))),_xlpm.ky,TRIM(IF(_xlpm.pk,"PK ","")&IF(_xlpm.fk,"FK ","")&IF(_xlpm.uq*(_xlpm.pk=0),_xlpm.ul,"")),_xlfn._xlws.FILTER(CHOOSE({1,2,3,4},_xlpm.ky,IF(_xlpm.fk,_xlpm.n&" → "&_xlpm.f,_xlpm.n),_xlpm.t,IF(_xlpm.nl="Yes","NULL","NOT NULL")),(_xlpm.n<>"")*(LEFT(_xlpm.n,1)<>"—")))} -> PK | R92: Id | S92: bigint | T92: NOT NULL
Q93: FK UQ1 | R93: TxnId → TxnCollateral.Id | S93: bigint | T93: NOT NULL
B94: =DefCollateralSecurityISIN!A1 -> DefCollateralSecurityISIN | Q94: UQ1 | R94: InstructionVersion | S94: int | T94: NOT NULL
B95: Anahtar | C95: ="Kolon / FK hedefi ("&ROWS(_xlfn.ANCHORARRAY(B96))&")" -> Kolon / FK hedefi (3) | D95: Tip | E95: Null | R95: SettlementTypeId | S95: int | T95: NULL
B96: {=_xlfn.LET(_xlpm.d,DefCollateralSecurityISIN!$A$7:$F$79,_xlpm.n,INDEX(_xlpm.d,,1),_xlpm.t,INDEX(_xlpm.d,,2),_xlpm.nl,INDEX(_xlpm.d,,3),_xlpm.c,INDEX(_xlpm.d,,5),_xlpm.f,INDEX(_xlpm.d,,6),_xlpm.pk,ISNUMBER(SEARCH("PK_",_xlpm.c))+ISNUMBER(SEARCH("(PK ile)",_xlpm.c)),_xlpm.fk,(LEFT(_xlpm.f,3)="Def")+(LEFT(_xlpm.f,3)="Txn"),_xlpm.qone,ISNUMBER(SEARCH("UQ1",_xlpm.c)),_xlpm.qtwo,ISNUMBER(SEARCH("UQ2",_xlpm.c)),_xlpm.qthree,ISNUMBER(SEARCH("UQ3",_xlpm.c)),_xlpm.uq,ISNUMBER(SEARCH("UQ",_xlpm.c)),_xlpm.ul,IF(_xlpm.qone,"UQ1",IF(_xlpm.qtwo,"UQ2",IF(_xlpm.qthree,"UQ3","UQ"))),_xlpm.ky,TRIM(IF(_xlpm.pk,"PK ","")&IF(_xlpm.fk,"FK ","")&IF(_xlpm.uq*(_xlpm.pk=0),_xlpm.ul,"")),_xlfn._xlws.FILTER(CHOOSE({1,2,3,4},_xlpm.ky,IF(_xlpm.fk,_xlpm.n&" → "&_xlpm.f,_xlpm.n),_xlpm.t,IF(_xlpm.nl="Yes","NULL","NOT NULL")),(_xlpm.n<>"")*(LEFT(_xlpm.n,1)<>"—")))} -> PK FK | C96: DefinitionId → DefCollateral.Id | D96: bigint | E96: NOT NULL | R96: PaymentInstructionTypeId | S96: int | T96: NULL
B97: PK | C97: ISIN | D97: nvarchar(12) | E97: NOT NULL | R97: WeSendSsiId | S97: bigint | T97: NULL
C98: IsActive | D98: bit | E98: NOT NULL | R98: TheyReceiveSsiId | S98: bigint | T98: NULL
R99: WeReceiveSsiId | S99: bigint | T99: NULL
R100: TheySendSsiId | S100: bigint | T100: NULL
R101: SendConfirmation | S101: bit | T101: NOT NULL
R102: SendPayment | S102: bit | T102: NOT NULL
R103: SendNoticeToReceive | S103: bit | T103: NOT NULL
...

Sheet DefCollateralAnnex
A1: DefCollateralAnnex | B1: (doküman adı: collateral_annex)
A2: Annex ekranı ana tablosu — sözleşmesel çerçeve. Her değişiklik yeni revizyon satırı (AnnexCode + RevisionNo), mevcut satır UPDATE edilmez.
A4: DB NESNELERİ: | B4: ✅ History + Trigger ZORUNLU (DefCollateralAnnexHistory + DefCollateralAnnexTrigger) · Id: bigint IDENTITY(1,1) · sp_UnverifiedDataCount + DefCountMonitoring (ekran rozetinde görünecekse)
A6: Kolon Adı | B6: Tip | C6: Null | D6: Default | E6: Index / Constraint | F6: FK Hedefi (FK → PK) | G6: Açıklama | H6: Anahtar / Açık Eşleşme
A7: Id | B7: bigint | C7: No | D7: IDENTITY(1,1) | E7: PK_DefCollateralAnnex | G7: 🔑 v4: IDENTITY. EF config'te `.UseIdentityColumn()` AÇIKÇA yazılmalı — yazılmazsa EF convention'ı int PK'yı ValueGeneratedOnAdd sayıp insert'i patlatıyor (MM'de ProductDefinition Create yolu bu yüzden kırık) | H7: PK
A8: AnnexCode | B8: nvarchar(50) | C8: No | E8: UQ1 · UQ_DefCollateralAnnex_AnnexCode | G8: Kullanıcıya gösterilen sabit iş kodu | H8: UQ1
A9: RevisionNo | B9: int | C9: No | D9: DEFAULT (1) | E9: (UQ1 ile birlikte) | G9: Sözleşmesel revizyon no — 🔴 MM'de emsali olmayan yeni pattern | H9: UQ1
A10: AnnexName | B10: nvarchar(200) | C10: No | G10: Açıklayıcı ad
A11: CustomerId | B11: int | C11: No | E11: IX_DefCollateralAnnex_CustomerId | F11: CusCustomer.Id | G11: Counterparty | H11: FK → CusCustomer.Id (PK)
A12: IsEnabled | B12: bit | C12: No | D12: DEFAULT (1) | E12: DF_DefCollateralAnnex_IsEnabled | G12: 🔑 v4: `Status` (DRAFT/ACTIVE/INACTIVE) KALDIRILDI — DRAFT≈StateId 16, ACTIVE≈StateId 18, yani %70'i tekrardı. Karşılığı olmayan tek değer INACTIVE idi; onu MM'in standart `IsEnabled` deseni karşılıyor (23 tabloda var). Kullanılabilirlik testi: `(StateId & 2) = 2 AND IsEnabled = 1`
A13: MasterAgreementText | B13: nvarchar(500) | C13: No | G13: Free-format sözleşme adı
A14: CollateralDocumentText | B14: nvarchar(500) | C14: No | G14: Free-format teminat dokümanı
A15: BaseCurrencyCode | B15: nvarchar(3) | C15: No | F15: Currency | G15: Raporlama/değerleme para birimi | H15: FK → Currency (doğal anahtar)
A16: Direction | B16: nvarchar(20) | C16: No | G16: BOTH / POST_ONLY / RECEIVE_ONLY
A17: ValidFrom | B17: date | C17: No | G17: Revizyon başlangıcı
A18: ValidTo | B18: date | C18: Yes | G18: Boşsa açık uçlu · ValidTo >= ValidFrom
A19: DisputeToleranceAmount | B19: decimal(38,10) | C19: No | D19: DEFAULT (0) | G19: Uyuşmazlık toleransı
A20: DisputeToleranceCurrencyCode | B20: nvarchar(3) | C20: No | F20: Currency | G20: Tolerans para birimi | H20: FK → Currency (doğal anahtar)
A21: StateId | B21: int | C21: No | D21: DEFAULT (18) | E21: DF_DefCollateralAnnex_StateId · IX_DefCollateralAnnex_StateId | G21: MakerChecker StateId (int, bitmask). Annex kullanılabilirliği `(StateId & 2) = 2 AND IsEnabled = 1` ile belirlenir; ayrı Status kolonu yoktur.
A22: StateMaker | B22: nvarchar(80) | C22: No | D22: DEFAULT ('system') | E22: DF_DefCollateralAnnex_StateMaker | G22: Son durum değişikliğini yapan kullanıcı (MakerCheckerEntity)
A23: StateDate | B23: datetime | C23: No | D23: DEFAULT (getdate()) | E23: DF_DefCollateralAnnex_StateDate | G23: Son durum değişikliği zamanı (MakerCheckerEntity)
A24: CreatedBy | B24: nvarchar(80) | C24: No | D24: DEFAULT (N'') | E24: DF_DefCollateralAnnex_CreatedBy | G24: ⚠️ MakerCheckerEntity bu alanı DECLARE ETMİYOR — entity sınıfına elle eklenmeli (doküman §10 her tabloda created_by istiyor)
A25: CreatedDate | B25: datetime | C25: No | D25: DEFAULT (getdate()) | E25: DF_DefCollateralAnnex_CreatedDate | G25: ⚠️ MakerCheckerEntity'de YOK — entity'ye elle eklenir

Sheet DefCollateralAnnexProductScope
A1: DefCollateralAnnexProductScope | B1: (doküman adı: annex_product_scope)
A2: Add Product penceresi — Annex kapsamındaki Product + SubProduct + MarginType kombinasyonu.
A4: DB NESNELERİ: | B4: ❌ History yok (parent revizyonu kapsıyor) · Id: bigint IDENTITY
A6: Kolon Adı | B6: Tip | C6: Null | D6: Default | E6: Index / Constraint | F6: FK Hedefi (FK → PK) | G6: Açıklama | H6: Anahtar / Açık Eşleşme
A7: Id | B7: bigint | C7: No | D7: IDENTITY(1,1) | E7: PK_DefCollateralAnnexProductScope | G7: Kapsam satırı | H7: PK
A8: AnnexId | B8: bigint | C8: No | E8: IX_DefCollateralAnnexProductScope_AnnexId | F8: DefCollateralAnnex.Id | G8: Annex revizyonu | H8: FK → DefCollateralAnnex.Id (PK)
A9: ProductCode | B9: nvarchar(50) | C9: No | F9: ⚠️ Ürün kataloğu (netleşmedi) | G9: FX / IR / Repo vb. | H9: Mantıksal FK → ️ Ürün kataloğu (netleşmedi)
A10: SubProductCode | B10: nvarchar(50) | C10: No | F10: ⚠️ Ürün kataloğu | G10: Forward / NDF / takas vb. | H10: Mantıksal FK → ️ Ürün kataloğu
A11: MarginType | B11: nvarchar(15) | C11: No | G11: VM / IM / IA / OTHER
A12: IsIncluded | B12: bit | C12: No | D12: DEFAULT (1) | E12: DF_DefCollateralAnnexProductScope_IsIncluded | G12: Kapsam göstergesi — satır silinmez, pasifleştirilir

Sheet DefCollateralAnnexMarginRule
A1: DefCollateralAnnexMarginRule | B1: (doküman adı: annex_margin_rule)
A2: Add Rule penceresi — seçili Product Scope satırı için Own/Counterparty bazlı Threshold/MTA/Rounding.
A4: DB NESNELERİ: | B4: ❌ History yok · Id: bigint IDENTITY
A6: Kolon Adı | B6: Tip | C6: Null | D6: Default | E6: Index / Constraint | F6: FK Hedefi (FK → PK) | G6: Açıklama | H6: Anahtar / Açık Eşleşme
A7: Id | B7: bigint | C7: No | D7: IDENTITY(1,1) | E7: PK_DefCollateralAnnexMarginRule | G7: Kural kimliği | H7: PK
A8: ProductScopeId | B8: bigint | C8: No | E8: UQ1 · UQ_DefCollateralAnnexMarginRule_ProductScopeId | F8: DefCollateralAnnexProductScope.Id | G8: 🔑 Pencereye bağlam olarak taşınır, kullanıcıdan istenmez | H8: UQ1 + FK → DefCollateralAnnexProductScope.Id (PK)
A9: Party | B9: nvarchar(20) | C9: No | E9: (UQ1 ile birlikte) | G9: OWN / COUNTERPARTY | H9: UQ1
A10: CurrencyCode | B10: nvarchar(3) | C10: No | E10: (UQ1 ile birlikte) | F10: Currency | G10: Kural para birimi | H10: UQ1 + FK → Currency (doğal anahtar)
A11: ThresholdAmount | B11: decimal(38,10) | C11: No | D11: DEFAULT (0) | G11: Teminatsız kabul edilen risk
A12: MtaAmount | B12: decimal(38,10) | C12: No | D12: DEFAULT (0) | G12: Minimum Transfer Amount
A13: RoundingAmount | B13: decimal(38,10) | C13: No | D13: DEFAULT (0) | G13: Yuvarlama adımı · > 0
A14: RoundingMethod | B14: nvarchar(12) | C14: No | G14: NEAREST / UP / DOWN

Sheet DefCollateral
A1: DefCollateral | B1: (doküman adı: collateral_definition)
A2: Definition ekranı ana tablosu — hangi nakit/menkul teminat kabul edilir. Her değişiklik yeni revizyon (CollateralCode + RevisionNo).
A4: DB NESNELERİ: | B4: ✅ History + Trigger ZORUNLU (DefCollateralHistory + DefCollateralTrigger) · Id: bigint IDENTITY(1,1) · sp_UnverifiedDataCount + DefCountMonitoring
A6: Kolon Adı | B6: Tip | C6: Null | D6: Default | E6: Index / Constraint | F6: FK Hedefi (FK → PK) | G6: Açıklama | H6: Anahtar / Açık Eşleşme
A7: Id | B7: bigint | C7: No | D7: IDENTITY(1,1) | E7: PK_DefCollateral | G7: bigint IDENTITY(1,1). EF config’te `.UseIdentityColumn()` açıkça yazılmalı. | H7: PK
A8: CollateralCode | B8: nvarchar(50) | C8: No | E8: UQ1 · UQ_DefCollateral_CollateralCode · IX_DefCollateral_CollateralCode | G8: Transaction ekranında seçilen kod | H8: UQ1
A9: RevisionNo | B9: int | C9: No | D9: DEFAULT (1) | E9: (UQ1 ile birlikte) | G9: Kural revizyonu | H9: UQ1
A10: CollateralName | B10: nvarchar(200) | C10: No | G10: Açıklayıcı ad
A11: AnnexId | B11: bigint | C11: Yes | F11: DefCollateralAnnex.Id | G11: Null = standalone tanım | H11: FK → DefCollateralAnnex.Id (PK)
A12: CustomerId | B12: int | C12: No | F12: CusCustomer.Id | G12: Annex varsa kilitli gelir | H12: FK → CusCustomer.Id (PK)
A13: CollateralType | B13: nvarchar(12) | C13: No | G13: CASH / SECURITY — alt tabloları belirler
A14: IsEnabled | B14: bit | C14: No | D14: DEFAULT (1) | E14: DF_DefCollateral_IsEnabled | G14: 🔑 v4: `Status` KALDIRILDI (DRAFT/ACTIVE StateId ile tekrar ediyordu). Yeni işlemde seçilebilirlik: `(StateId & 2) = 2 AND IsEnabled = 1`
A15: EligibilityDirection | B15: nvarchar(20) | C15: No | G15: BOTH / POST_ONLY / RECEIVE_ONLY
A16: ValuationCurrencyCode | B16: nvarchar(3) | C16: No | F16: Currency | G16: Eligible value para birimi | H16: FK → Currency (doğal anahtar)
A17: ValidFrom | B17: date | C17: No
A18: ValidTo | B18: date | C18: Yes | G18: ValidTo >= ValidFrom
A19: StateId | B19: int | C19: No | D19: DEFAULT (18) | E19: DF_DefCollateral_StateId · IX_DefCollateral_StateId | G19: 🔑 `int` — koddan doğrulandı: MakerCheckerEntity.StateId **int**, FlowEntity.StateId **long**. Maker-checker BITMASK; Draft/Active/Inactive iş durumu AYRI kolonda (Status)
A20: StateMaker | B20: nvarchar(80) | C20: No | D20: DEFAULT ('system') | E20: DF_DefCollateral_StateMaker | G20: Son durum değişikliğini yapan kullanıcı (MakerCheckerEntity)
A21: StateDate | B21: datetime | C21: No | D21: DEFAULT (getdate()) | E21: DF_DefCollateral_StateDate | G21: Son durum değişikliği zamanı (MakerCheckerEntity)
A22: CreatedBy | B22: nvarchar(80) | C22: No | D22: DEFAULT (N'') | E22: DF_DefCollateral_CreatedBy | G22: ⚠️ MakerCheckerEntity bu alanı DECLARE ETMİYOR — entity sınıfına elle eklenmeli (doküman §10 her tabloda created_by istiyor)
A23: CreatedDate | B23: datetime | C23: No | D23: DEFAULT (getdate()) | E23: DF_DefCollateral_CreatedDate | G23: ⚠️ MakerCheckerEntity'de YOK — entity'ye elle eklenir

Sheet DefCollateralEligibleCurrency
A1: DefCollateralEligibleCurrency | B1: (doküman adı: collateral_eligible_currency)
A2: Cash Definition için izinli işlem para birimleri.
A4: DB NESNELERİ: | B4: ❌ History yok · Composite PK (Id kolonu YOK)
A6: Kolon Adı | B6: Tip | C6: Null | D6: Default | E6: Index / Constraint | F6: FK Hedefi (FK → PK) | G6: Açıklama | H6: Anahtar / Açık Eşleşme
A7: DefinitionId | B7: bigint | C7: No | E7: PK_DefCollateralEligibleCurrency | F7: DefCollateral.Id | G7: Composite PK #1 | H7: PK + FK → DefCollateral.Id (PK)
A8: CurrencyCode | B8: nvarchar(3) | C8: No | E8: (PK ile) | F8: Currency | G8: Composite PK #2 | H8: PK + FK → Currency (doğal anahtar)
A9: FxAdjustmentRate | B9: decimal(18,10) | C9: No | D9: DEFAULT (0) | G9: Sözleşmesel FX adjustment · 0..1
A10: IsActive | B10: bit | C10: No | D10: DEFAULT (1) | G10: Yeni işlemde seçilebilirlik

Sheet DefCollateralCashTerms
A1: DefCollateralCashTerms | B1: (doküman adı: collateral_cash_terms)
A2: Cash Definition faiz paneli. Faz-1'de yalnız saklanır, tahakkuk motoru YOK (doküman §5.1.4).
A4: DB NESNELERİ: | B4: ❌ History yok · PK = FK (ayrı Id kolonu YOK) · Satır opsiyonel (1:0..1)
A6: Kolon Adı | B6: Tip | C6: Null | D6: Default | E6: Index / Constraint | F6: FK Hedefi (FK → PK) | G6: Açıklama | H6: Anahtar / Açık Eşleşme
A7: DefinitionId | B7: bigint | C7: No | E7: PK_DefCollateralCashTerms | F7: DefCollateral.Id | G7: PK = FK | H7: PK + FK → DefCollateral.Id (PK)
A8: RateType | B8: nvarchar(20) | C8: Yes | G8: FLOATING / FIXED / INTEREST_FREE
A9: ReferenceRateCode | B9: nvarchar(30) | C9: Yes | F9: 🔴 Referans oran kataloğu (yeni) | G9: FLOATING ise zorunlu | H9: Mantıksal FK → _xDD34_ Referans oran kataloğu (yeni)
A10: SpreadBps | B10: decimal(18,10) | C10: Yes | G10: ⚠️ Baz puan — 150 = %1.5. Kesir mi ham bps mi, kod tarafında NET tanımla (100x hata riski)
A11: FixedRate | B11: decimal(18,10) | C11: Yes | G11: FIXED ise zorunlu
A12: CompoundingMethod | B12: nvarchar(25) | C12: Yes | G12: DAILY_COMPOUNDED / SIMPLE / NONE
A13: DayCount | B13: nvarchar(15) | C13: Yes | G13: ACT_360 / ACT_365 / THIRTY_360
A14: PaymentFrequency | B14: nvarchar(25) | C14: Yes | G14: MONTHLY / QUARTERLY / ON_RETURN
A15: BusinessDayRule | B15: nvarchar(25) | C15: Yes | G15: MOD_FOLLOWING / FOLLOWING / PRECEDING
A16: IsNegativeRateAllowed | B16: bit | C16: Yes | G16: Negatif referans oran davranışı

Sheet DefCollateralSettlementMap
A1: DefCollateralSettlementMap | B1: (doküman adı: collateral_settlement_mapping)
A2: Cash veya Security Definition için settlement/hesap/SSI eşlemesi, TransactionType bazlı. "Map" soneki MM eşleme tablosu konvansiyonu.
A4: DB NESNELERİ: | B4: ❌ History yok · Id: bigint IDENTITY
A6: Kolon Adı | B6: Tip | C6: Null | D6: Default | E6: Index / Constraint | F6: FK Hedefi (FK → PK) | G6: Açıklama | H6: Anahtar / Açık Eşleşme
A7: Id | B7: bigint | C7: No | D7: IDENTITY(1,1) | E7: PK_DefCollateralSettlementMap | H7: PK
A8: DefinitionId | B8: bigint | C8: No | E8: IX_DefCollateralSettlementMap_DefinitionId | F8: DefCollateral.Id | H8: FK → DefCollateral.Id (PK)
A9: TransactionType | B9: nvarchar(12) | C9: No | G9: INCREASE / DECREASE
A10: CurrencyCode | B10: nvarchar(3) | C10: Yes | F10: Currency | G10: Cash için | H10: FK → Currency (doğal anahtar)
A11: SettlementLocationCode | B11: nvarchar(40) | C11: Yes | F11: 🔴 CSD/ICSD kataloğu (yeni) | G11: Takasbank / Euroclear / Clearstream | H11: Mantıksal FK → _xDD34_ CSD/ICSD kataloğu (yeni)
A12: SettlementAccountId | B12: int | C12: Yes | F12: ⚠️ Hesap master (netleşmedi) | G12: Nakit veya custody hesabı | H12: Mantıksal FK → ️ Hesap master (netleşmedi)
A13: InterestAccountId | B13: int | C13: Yes | F13: ⚠️ Hesap master | G13: Cash faiz hesabı | H13: Mantıksal FK → ️ Hesap master
A14: SsiId | B14: bigint | C14: Yes | F14: 🔴 SSI master (yeni) | G14: Standing settlement instruction | H14: Mantıksal FK → _xDD34_ SSI master (yeni)
A15: PaymentRouteCode | B15: nvarchar(40) | C15: Yes | F15: 🔴 Rota konfigürasyonu (yeni) | G15: pacs / non-CBPR+ / local | H15: Mantıksal FK → _xDD34_ Rota konfigürasyonu (yeni)

Sheet DefCollateralSecurityRule
A1: DefCollateralSecurityRule | B1: (doküman adı: collateral_security_rule)
A2: Security Definition — kural bazlı menkul uygunluğu (Security Scope = Eligibility Rule).
A4: DB NESNELERİ: | B4: ❌ History yok · Id: bigint IDENTITY
A6: Kolon Adı | B6: Tip | C6: Null | D6: Default | E6: Index / Constraint | F6: FK Hedefi (FK → PK) | G6: Açıklama | H6: Anahtar / Açık Eşleşme
A7: Id | B7: bigint | C7: No | D7: IDENTITY(1,1) | E7: PK_DefCollateralSecurityRule | H7: PK
A8: DefinitionId | B8: bigint | C8: No | E8: IX_DefCollateralSecurityRule_DefinitionId | F8: DefCollateral.Id | H8: FK → DefCollateral.Id (PK)
A9: SecurityTypeCode | B9: nvarchar(40) | C9: No | F9: 🔴 Menkul master (yeni) | G9: Kabul edilen menkul sınıfı | H9: Mantıksal FK → _xDD34_ Menkul master (yeni)
A10: IssuerTypeCode | B10: nvarchar(40) | C10: No | F10: 🔴 Menkul master (yeni) | G10: Sovereign / Supranational / Bank / Corporate | H10: Mantıksal FK → _xDD34_ Menkul master (yeni)
A11: CountryOfRiskCode | B11: nvarchar(3) | C11: Yes | F11: ⚠️ DefCountry (MM'de var mı kontrol) | G11: ISO ülke kodu | H11: Mantıksal FK → ️ DefCountry (MM'de var mı kontrol)
A12: EligibleCurrencyCode | B12: nvarchar(3) | C12: No | F12: Currency | G12: İhraç para birimi | H12: FK → Currency (doğal anahtar)
A13: MinimumRatingCode | B13: nvarchar(30) | C13: Yes | F13: 🔴 Rating master (yeni) | G13: En düşük kredi notu | H13: Mantıksal FK → _xDD34_ Rating master (yeni)
A14: MaxRemainingMaturityDays | B14: int | C14: Yes | G14: Kalan vade sınırı · > 0
A15: IsActive | B15: bit | C15: No | D15: DEFAULT (1)

Sheet DefCollateralSecurityISIN
A1: DefCollateralSecurityISIN | B1: (doküman adı: collateral_security_isin)
A2: Security Definition — tekil uygun kıymet listesi (Security Scope = Specific ISIN).
A4: DB NESNELERİ: | B4: ❌ History yok · Composite PK (Id kolonu YOK)
A6: Kolon Adı | B6: Tip | C6: Null | D6: Default | E6: Index / Constraint | F6: FK Hedefi (FK → PK) | G6: Açıklama | H6: Anahtar / Açık Eşleşme
A7: DefinitionId | B7: bigint | C7: No | E7: PK_DefCollateralSecurityISIN | F7: DefCollateral.Id | G7: Composite PK #1 | H7: PK + FK → DefCollateral.Id (PK)
A8: ISIN | B8: nvarchar(12) | C8: No | E8: (PK ile) | F8: 🔴 Menkul master (yeni) | G8: Composite PK #2 · ISO 6166, 12 karakter | H8: PK + Mantıksal FK → _xDD34_ Menkul master (yeni)
A9: IsActive | B9: bit | C9: No | D9: DEFAULT (1)

Sheet DefCollateralSecurityTerms
A1: DefCollateralSecurityTerms | B1: (doküman adı: collateral_security_terms)
A2: Security Definition değerleme/haircut paneli.
A4: DB NESNELERİ: | B4: ❌ History yok · PK = FK (ayrı Id kolonu YOK) · Satır opsiyonel (1:0..1)
A6: Kolon Adı | B6: Tip | C6: Null | D6: Default | E6: Index / Constraint | F6: FK Hedefi (FK → PK) | G6: Açıklama | H6: Anahtar / Açık Eşleşme
A7: DefinitionId | B7: bigint | C7: No | E7: PK_DefCollateralSecurityTerms | F7: DefCollateral.Id | G7: PK = FK | H7: PK + FK → DefCollateral.Id (PK)
A8: PriceSource | B8: nvarchar(30) | C8: Yes | G8: MARKET_DATA / CUSTODIAN / MANUAL_APPROVED
A9: PriceType | B9: nvarchar(25) | C9: Yes | G9: DIRTY / CLEAN_PLUS_ACCRUED
A10: HaircutMethod | B10: nvarchar(30) | C10: Yes | G10: FIXED / SCHEDULE / EXTERNAL
A11: AssetHaircutRate | B11: decimal(18,10) | C11: Yes | G11: Varlık haircut · 0..1
A12: FxHaircutRate | B12: decimal(18,10) | C12: Yes | G12: FX haircut · 0..1
A13: MinimumNominal | B13: decimal(38,10) | C13: Yes | G13: En küçük kabul edilebilir nominal
A14: IncomeTreatment | B14: nvarchar(30) | C14: Yes | G14: PASS_THROUGH / APPLY_EXPOSURE / PER_AGREEMENT
A15: CorporateActionHandling | B15: nvarchar(35) | C15: Yes | G15: INSTRUCTION_REQUIRED / AUTO_PASS_THROUGH

Sheet TxnCollateral
A1: TxnCollateral | B1: (doküman adı: collateral_transaction)
A2: İşlem ekranı ana tablosu — Increase/Decrease ekonomik hareketi. MM'in TxnMM/TxnTawarruq emsaliyle birebir aynı audit bloğunu taşır.
A4: DB NESNELERİ: | B4: 🔴 Id DefNumberGen'den (IDENTITY DEĞİL) — DefNumberGen satırı: Definition = 'Txn Collateral Id' · ✅ History + Trigger ZORUNLU · ✅ FlowSet + FlowTransition satırları · ✅ sp_UnverifiedDataCount_TxnCollateral + DefCountMonitoring · LogicalReference ayrı sayaçtan (sp_GetNewRefNumber)
A6: Kolon Adı | B6: Tip | C6: Null | D6: Default | E6: Index / Constraint | F6: FK Hedefi (FK → PK) | G6: Açıklama | H6: Anahtar / Açık Eşleşme
A7: Id | B7: bigint | C7: No | D7: 🔴 DefNumberGen | E7: PK_TxnCollateral | G7: 🔴 IDENTITY DEĞİL — sayaçtan rezerve edilir (db-script.md §6) | H7: PK
A8: LogicalReference | B8: nvarchar(80) | C8: No | E8: UQ1 · UQ_TxnCollateral_LogicalReference | G8: Sistem üretir: prefix + yön + tarih + sıra (sp_GetNewRefNumber). 🔑 Dokümanda yok, MM emsalinden eklendi (UQ_TxnMM_LogicalReference) — dokümanın logical_reference'ı farklı şey, o ExternalReference oldu | H8: UQ1
A9: TransactionReference | B9: nvarchar(60) | C9: No | E9: UQ2 · UQ_TxnCollateral_TransactionReference | G9: Kullanıcıya gösterilen referans | H9: UQ2
A10: DefinitionId | B10: bigint | C10: No | E10: IX_TxnCollateral_DefinitionId_ValueDate | F10: DefCollateral.Id | G10: 🔑 Kullanılan immutable Definition REVİZYONU | H10: FK → DefCollateral.Id (PK)
A11: AnnexId | B11: bigint | C11: Yes | F11: DefCollateralAnnex.Id | G11: Kullanılan immutable Annex revizyonu | H11: FK → DefCollateralAnnex.Id (PK)
A12: CustomerId | B12: int | C12: No | E12: IX_TxnCollateral_CustomerId | F12: CusCustomer.Id | G12: İşlem anındaki karşı taraf (snapshot) | H12: FK → CusCustomer.Id (PK)
A13: PortfolioId | B13: int | C13: No | F13: PrfPortfolio.Id | G13: Muhasebe/raporlama portföyü | H13: FK → PrfPortfolio.Id (PK)
A14: SourceSystem | B14: nvarchar(50) | C14: Yes | E14: UQ3 · UQ_TxnCollateral_SourceSystem | G14: Harici kaynak kodu | H14: UQ3
A15: ExternalReference | B15: nvarchar(100) | C15: Yes | E15: (UQ3 ile birlikte) | G15: Harici call/operasyon referansı — doküman: logical_reference. 🔑 Bizim LogicalReference ile KARIŞTIRMA | H15: UQ3
A16: TradeDate | B16: date | C16: No | G16: İşlem tarihi
A17: ValueDate | B17: date | C17: No | E17: (IX ile) | G17: Settlement tarihi
A18: InputDate | B18: datetime | C18: No | D18: DEFAULT (getdate()) | G18: Kaydın sisteme giriş zamanı
A19: TransactionType | B19: nvarchar(12) | C19: No | G19: INCREASE / DECREASE
A20: MarginType | B20: nvarchar(15) | C20: No | G20: VM / IM / IA / OTHER
A21: CollateralType | B21: nvarchar(12) | C21: No | G21: CASH / SECURITY — hangi alt tip satırı olacağını belirler
A22: LifecycleStatus | B22: nvarchar(30) | C22: No | D22: DEFAULT ('DRAFT') | G22: Settlement yaşam döngüsü (SENT/ACCEPTED/SETTLED...) — StateId'den AYRI, UI'da düzenlenmez
A23: EconomicVersion | B23: int | C23: No | D23: DEFAULT (1) | E23: DF_TxnCollateral_EconomicVersion | G23: Reversal/amendment zinciri
A24: ReversalOfId | B24: bigint | C24: Yes | F24: TxnCollateral.Id (self) | G24: Ters işlem ilişkisi | H24: FK → TxnCollateral.Id (self) (PK)
A25: Trader | B25: nvarchar(80) | C25: No | D25: DEFAULT ('') | E25: DF_TxnCollateral_Trader | G25: İşlemi yapan dealer. 🔑 CreatedBy'dan AYRI bir iş alanı — MM TxnTawarruq emsali
A26: StateId | B26: bigint | C26: No | D26: DEFAULT (18) | E26: DF_TxnCollateral_StateId · IX_TxnCollateral_StateId | G26: Maker-checker BITMASK: 16 Input · 18 InputVerified · 17 InputRejected · 20 Delete · 22 DeleteVerified · 24 Edit (bkz 00_Sabitler)
A27: StateMaker | B27: nvarchar(80) | C27: No | D27: DEFAULT ('system') | E27: DF_TxnCollateral_StateMaker | G27: Son durum değişikliğini yapan kullanıcı
A28: StateDate | B28: datetime | C28: No | D28: DEFAULT (getdate()) | E28: DF_TxnCollateral_StateDate | G28: Son durum değişikliği zamanı
A29: CreatedBy | B29: nvarchar(80) | C29: No | D29: DEFAULT (N'') | E29: DF_TxnCollateral_CreatedBy | G29: Kaydı ilk açan kullanıcı
A30: CreatedDate | B30: datetime | C30: No | D30: DEFAULT (getdate()) | E30: DF_TxnCollateral_CreatedDate | G30: İlk kayıt zamanı
A31: PreviousStateId | B31: bigint | C31: Yes | G31: Önceki durum
A32: PreviousStateMaker | B32: nvarchar(80) | C32: Yes | G32: Önceki durumu yapan kullanıcı
A33: PreviousStateDate | B33: datetime | C33: Yes | G33: Önceki durum zamanı
A34: FlowId | B34: bigint | C34: No | D34: DEFAULT (0) | E34: DF_TxnCollateral_FlowId | G34: FlowSet örnek kimliği — CollateralTransactionFlow (bkz 00_DB_Nesneleri)
A35: LastActionId | B35: bigint | C35: No | D35: DEFAULT (0) | E35: DF_TxnCollateral_LastActionId | G35: Son uygulanan flow aksiyonu (2 Create · 4 Update · 8 Delete · 16 Verify · 32 Reject)
A36: PreviousActionId | B36: bigint | C36: Yes | G36: Bir önceki flow aksiyonu — FlowEntity.UpdateStates() bunu otomatik dolduruyor

Sheet TxnCollateralCash
A1: TxnCollateralCash | B1: (doküman adı: collateral_cash_transaction)
A2: İşlem alt tipi — Cash. CollateralType = CASH ise bu satır vardır, Security satırı OLMAZ.
A4: DB NESNELERİ: | B4: ❌ History yok (parent TxnCollateralHistory kapsıyor) · PK = FK TxnId · Ayrı Id kolonu YOK — MM TxnMMDetail emsali
A6: Kolon Adı | B6: Tip | C6: Null | D6: Default | E6: Index / Constraint | F6: FK Hedefi (FK → PK) | G6: Açıklama | H6: Anahtar / Açık Eşleşme
A7: TxnId | B7: bigint | C7: No | E7: PK_TxnCollateralCash | F7: TxnCollateral.Id | G7: PK = FK · MM'in standart alt tablo FK adı | H7: PK + FK → TxnCollateral.Id (PK)
A8: Amount | B8: decimal(38,10) | C8: No | G8: Transfer edilen nakit tutar · > 0
A9: CurrencyCode | B9: nvarchar(3) | C9: No | E9: IX_TxnCollateralCash_CurrencyCode | F9: Currency | G9: Settlement para birimi (Definition'ın izin verdiği listeden) | H9: FK → Currency (doğal anahtar)
A10: CurrentBalanceBefore | B10: decimal(38,10) | C10: No | D10: DEFAULT (0) | G10: 🔑 İşlem öncesi bakiye SNAPSHOT'ı — sonradan kanıt için
A11: ValuationCurrencyCode | B11: nvarchar(3) | C11: No | F11: Currency | G11: Değerleme para birimi | H11: FK → Currency (doğal anahtar)
A12: IsFxConversionRequired | B12: bit | C12: No | D12: DEFAULT (0) | G12: CurrencyCode <> ValuationCurrencyCode
A13: FxRate | B13: decimal(38,10) | C13: No | D13: DEFAULT (1) | G13: Valuation ccy / transaction ccy · > 0
A14: FxAdjustmentRate | B14: decimal(18,10) | C14: No | D14: DEFAULT (0) | E14: DF_TxnCollateralCash_FxAdjustmentRate | G14: 0..1 · 🔑 Cash'te asset haircut YOK, yalnız FX adjustment
A15: TransactionValue | B15: decimal(38,10) | C15: No | G15: Amount × FxRate (brüt)
A16: AdjustedEligibleValue | B16: decimal(38,10) | C16: No | G16: TransactionValue × (1 − FxAdjustmentRate)

Sheet TxnCollateralSecurity
A1: TxnCollateralSecurity | B1: (doküman adı: collateral_security_transaction)
A2: İşlem alt tipi — Security. CollateralType = SECURITY ise bu satır vardır, Cash satırı OLMAZ.
A4: DB NESNELERİ: | B4: ❌ History yok · PK = FK TxnId · Ayrı Id kolonu YOK
A6: Kolon Adı | B6: Tip | C6: Null | D6: Default | E6: Index / Constraint | F6: FK Hedefi (FK → PK) | G6: Açıklama | H6: Anahtar / Açık Eşleşme
A7: TxnId | B7: bigint | C7: No | E7: PK_TxnCollateralSecurity | F7: TxnCollateral.Id | G7: PK = FK | H7: PK + FK → TxnCollateral.Id (PK)
A8: ISIN | B8: nvarchar(12) | C8: No | E8: IX_TxnCollateralSecurity_ISIN | F8: 🔴 Menkul master (yeni) | G8: Teslim/alım konusu kıymet | H8: Mantıksal FK → _xDD34_ Menkul master (yeni)
A9: Nominal | B9: decimal(38,10) | C9: No | G9: İşlem nominali · > 0
A10: CurrentNominalBefore | B10: decimal(38,10) | C10: No | D10: DEFAULT (0) | G10: İşlem öncesi nominal snapshot
A11: Price | B11: decimal(38,10) | C11: No | G11: Onaylı kaynaktan fiyat (snapshot)
A12: PriceDate | B12: date | C12: No | G12: Fiyatın iş tarihi
A13: PriceFactor | B13: decimal(18,10) | C13: No | D13: DEFAULT (100) | G13: Tahvilde genellikle 100 · > 0
A14: MarketValue | B14: decimal(38,10) | C14: No | G14: Nominal × Price / PriceFactor (haircut öncesi)
A15: ValuationCurrencyCode | B15: nvarchar(3) | C15: No | F15: Currency | H15: FK → Currency (doğal anahtar)
A16: AssetHaircutRate | B16: decimal(18,10) | C16: No | D16: DEFAULT (0) | G16: 0..1 · işlem anı snapshot
A17: FxHaircutRate | B17: decimal(18,10) | C17: No | D17: DEFAULT (0) | G17: 0..1 · işlem anı snapshot
A18: FxRate | B18: decimal(38,10) | C18: No | D18: DEFAULT (1) | G18: > 0
A19: AdjustedEligibleValue | B19: decimal(38,10) | C19: No | G19: MarketValue × FxRate × (1−AssetHaircut) × (1−FxHaircut)

Sheet TxnCollateralValuation
A1: TxnCollateralValuation | B1: (doküman adı: collateral_valuation_snapshot)
A2: Verify/EOD/Settlement anlarında kullanılan kur-fiyat-haircut-eligible value değerlerinin değiştirilemez kaydı. MM: TxnMMDailyCalculation / LoanRevaluation emsali.
A4: DB NESNELERİ: | B4: ❌ History yok (zaten append-only/immutable) · Id: bigint IDENTITY · DefNumberGen GEREKMEZ
A6: Kolon Adı | B6: Tip | C6: Null | D6: Default | E6: Index / Constraint | F6: FK Hedefi (FK → PK) | G6: Açıklama | H6: Anahtar / Açık Eşleşme
A7: Id | B7: bigint | C7: No | D7: IDENTITY(1,1) | E7: PK_TxnCollateralValuation | H7: PK
A8: TxnId | B8: bigint | C8: No | E8: IX_TxnCollateralValuation_TxnId_Stage | F8: TxnCollateral.Id | H8: FK → TxnCollateral.Id (PK)
A9: SnapshotStage | B9: nvarchar(20) | C9: No | E9: (IX ile) | G9: ENTRY / VERIFY / EOD / SETTLEMENT
A10: FxRate | B10: decimal(38,10) | C10: Yes | G10: Kullanılan kur · > 0
A11: RateConvention | B11: nvarchar(30) | C11: Yes | G11: Örn. TRY_PER_EUR — kur yönünü kanıtlar
A12: Price | B12: decimal(38,10) | C12: Yes | G12: Security fiyatı
A13: PriceDate | B13: date | C13: Yes
A14: AssetHaircutRate | B14: decimal(18,10) | C14: Yes | G14: 0..1
A15: FxAdjustmentRate | B15: decimal(18,10) | C15: Yes | G15: 0..1 (Cash)
A16: FxHaircutRate | B16: decimal(18,10) | C16: Yes | G16: 0..1 (Security)
A17: GrossValue | B17: decimal(38,10) | C17: No | G17: Haircut/adjustment öncesi
A18: EligibleValue | B18: decimal(38,10) | C18: No | G18: Net kabul edilebilir değer
A19: ValuationCurrencyCode | B19: nvarchar(3) | C19: No | F19: Currency | H19: FK → Currency (doğal anahtar)
A20: AsOfDate | B20: datetime | C20: No | D20: DEFAULT (getdate()) | G20: Snapshot zamanı
A21: SourceRefHash | B21: nvarchar(128) | C21: Yes | G21: Kaynak verinin güvenli özeti

Sheet TxnCollateralLimit
A1: TxnCollateralLimit | B1: (doküman adı: collateral_limit_snapshot)
A2: Limit servisinin ENTRY ve VERIFY anlarındaki kararının değiştirilemez kaydı. Verify blokajı blocking_flag'den gelir, ekran yorumlamaz.
A4: DB NESNELERİ: | B4: ❌ History yok · Id: bigint IDENTITY
A6: Kolon Adı | B6: Tip | C6: Null | D6: Default | E6: Index / Constraint | F6: FK Hedefi (FK → PK) | G6: Açıklama | H6: Anahtar / Açık Eşleşme
A7: Id | B7: bigint | C7: No | D7: IDENTITY(1,1) | E7: PK_TxnCollateralLimit | H7: PK
A8: TxnId | B8: bigint | C8: No | E8: UQ1 · UQ_TxnCollateralLimit_TxnId | F8: TxnCollateral.Id | H8: UQ1 + FK → TxnCollateral.Id (PK)
A9: SnapshotStage | B9: nvarchar(20) | C9: No | E9: (UQ1 ile birlikte) | G9: ENTRY / VERIFY | H9: UQ1
A10: LimitStatus | B10: nvarchar(25) | C10: No | G10: CONTROL_ACTIVE / CONTROL_INACTIVE
A11: AvailabilityStatus | B11: nvarchar(20) | C11: No | G11: AVAILABLE / UNAVAILABLE / WARNING
A12: DecisionCode | B12: nvarchar(40) | C12: No | G12: Limit servisinin karar kodu
A13: IsBlocking | B13: bit | C13: No | D13: DEFAULT (0) | G13: 🔴 Verify blokajının TEK kaynağı
A14: CustomerId | B14: int | C14: No | F14: CusCustomer.Id | G14: Snapshot | H14: FK → CusCustomer.Id (PK)
A15: CustomerNo | B15: nvarchar(50) | C15: No | G15: Limit sistemindeki müşteri no
A16: LimitCurrencyCode | B16: nvarchar(3) | C16: No | F16: Currency | H16: FK → Currency (doğal anahtar)
A17: CountryLimit | B17: decimal(38,10) | C17: No | D17: DEFAULT (0)
A18: TotalLimit | B18: decimal(38,10) | C18: No | D18: DEFAULT (0)
A19: UsedLimit | B19: decimal(38,10) | C19: No | D19: DEFAULT (0)
A20: AvailableLimit | B20: decimal(38,10) | C20: No | D20: DEFAULT (0)
A21: UtilizationRate | B21: decimal(18,10) | C21: No | D21: DEFAULT (0) | G21: 0..1
A22: RiskAmount | B22: decimal(38,10) | C22: No | D22: DEFAULT (0) | G22: İşlemin limite etkisi — ön yüz tahmin etmez
A23: AsOfDate | B23: datetime | C23: No | D23: DEFAULT (getdate())
A24: SourceRefHash | B24: nvarchar(128) | C24: Yes

Sheet TxnCollateralPaymentInstruction
A1: TxnCollateralPaymentInstruction | B1: (doküman adı: collateral_payment_instruction)
A2: Near Payment Instructions — yön bazlı SSI çifti + gönderim seçenekleri, sürümlü. 🔑 SettlementType ve PaymentInstructionType MM'de ZATEN VAR olan tablolara FK — yeni tablo açma.
A4: DB NESNELERİ: | B4: ❌ History yok (sürüm artışı yeni satır) · Id: bigint IDENTITY
A6: Kolon Adı | B6: Tip | C6: Null | D6: Default | E6: Index / Constraint | F6: FK Hedefi (FK → PK) | G6: Açıklama | H6: Anahtar / Açık Eşleşme
A7: Id | B7: bigint | C7: No | D7: IDENTITY(1,1) | E7: PK_TxnCollateralPaymentInstruction | H7: PK
A8: TxnId | B8: bigint | C8: No | E8: UQ1 · UQ_TxnCollateralPaymentInstruction_TxnId | F8: TxnCollateral.Id | H8: UQ1 + FK → TxnCollateral.Id (PK)
A9: InstructionVersion | B9: int | C9: No | D9: DEFAULT (1) | E9: (UQ1 ile birlikte) | G9: Verify sonrası overwrite edilmez, yeni sürüm açılır | H9: UQ1
A10: SettlementTypeId | B10: int | C10: Yes | F10: ✅ SettlementType.Id (MM'de VAR) | G10: Gross / Netting | H10: FK → ✅ SettlementType.Id (MM'de VAR) (PK)
A11: PaymentInstructionTypeId | B11: int | C11: Yes | F11: ✅ PaymentInstructionType.Id (MM'de VAR) | G11: B2B / A2A / Vostro / A2AD | H11: FK → ✅ PaymentInstructionType.Id (MM'de VAR) (PK)
A12: WeSendSsiId | B12: bigint | C12: Yes | F12: 🔴 SSI master (yeni) | G12: DECREASE'de ZORUNLU | H12: Mantıksal FK → _xDD34_ SSI master (yeni)
A13: TheyReceiveSsiId | B13: bigint | C13: Yes | F13: 🔴 SSI master | G13: DECREASE'de ZORUNLU | H13: Mantıksal FK → _xDD34_ SSI master
A14: WeReceiveSsiId | B14: bigint | C14: Yes | F14: 🔴 SSI master | G14: INCREASE'de ZORUNLU | H14: Mantıksal FK → _xDD34_ SSI master
A15: TheySendSsiId | B15: bigint | C15: Yes | F15: 🔴 SSI master | G15: INCREASE'de ZORUNLU | H15: Mantıksal FK → _xDD34_ SSI master
A16: SendConfirmation | B16: bit | C16: No | D16: DEFAULT (0) | E16: DF_TxnCollateralPaymentInstruction_SendConfirmation
A17: SendPayment | B17: bit | C17: No | D17: DEFAULT (0) | E17: DF_TxnCollateralPaymentInstruction_SendPayment | G17: Yalnız DECREASE akışında aktif
A18: SendNoticeToReceive | B18: bit | C18: No | D18: DEFAULT (0) | E18: DF_TxnCollateralPaymentInstruction_SendNoticeToReceive | G18: Yalnız INCREASE akışında aktif
A19: Instructions | B19: nvarchar(500) | C19: Yes | G19: ⚠️ MM'de benzer alan Fimple'a 250 karakter olarak gidiyor — uzunluk sınırını uçta doğrula
A20: CreatedBy | B20: nvarchar(80) | C20: No | D20: DEFAULT (N'')
A21: CreatedDate | B21: datetime | C21: No | D21: DEFAULT (getdate())

Sheet TxnCollateralMessage
A1: TxnCollateralMessage | B1: (doküman adı: collateral_message)
A2: Üretilen ödeme/menkul mesajının başlık kaydı (pacs.009, MT202, sese.023, MT54x). MM: PaymentMessage + ExternalMM/SyncMessage deseninin muadili.
A4: DB NESNELERİ: | B4: ❌ History yok · Id: bigint IDENTITY · 🔑 Outbox deseni: Verify ile AYNI DB transaction'ında yazılır
A6: Kolon Adı | B6: Tip | C6: Null | D6: Default | E6: Index / Constraint | F6: FK Hedefi (FK → PK) | G6: Açıklama | H6: Anahtar / Açık Eşleşme
A7: Id | B7: bigint | C7: No | D7: IDENTITY(1,1) | E7: PK_TxnCollateralMessage | H7: PK
A8: TxnId | B8: bigint | C8: No | E8: IX_TxnCollateralMessage_TxnId | F8: TxnCollateral.Id | H8: FK → TxnCollateral.Id (PK)
A9: MessageFamily | B9: nvarchar(20) | C9: No | G9: PAYMENT / SECURITIES
A10: MessageType | B10: nvarchar(30) | C10: No | G10: PACS009_CORE / MT202_NON_CBPR / SESE023 / MT54x — 🔑 kullanıcı seçmez, route belirler
A11: MessagePurpose | B11: nvarchar(25) | C11: No | G11: SETTLEMENT / CANCELLATION / CONFIRMATION
A12: BusinessService | B12: nvarchar(60) | C12: Yes | G12: CBPR+ veya yerel servis adı
A13: SenderBic | B13: nvarchar(11) | C13: Yes
A14: ReceiverBic | B14: nvarchar(11) | C14: Yes
A15: SettlementAccountId | B15: int | C15: Yes | F15: ⚠️ Hesap master | H15: Mantıksal FK → ️ Hesap master
A16: Amount | B16: decimal(38,10) | C16: Yes | G16: 🔑 İşlem tutarı gider, valuation tutarı GİTMEZ
A17: CurrencyCode | B17: nvarchar(3) | C17: Yes | F17: Currency | H17: FK → Currency (doğal anahtar)
A18: MessageIdentifier | B18: nvarchar(80) | C18: No | G18: MsgId / sender reference
A19: InstructionId | B19: nvarchar(80) | C19: Yes
A20: UETR | B20: uniqueidentifier | C20: Yes | E20: UQ1 · UQ_TxnCollateralMessage_UETR (filtered) | G20: 🔑 SWIFT'in zorunlu kıldığı GERÇEK UUID — ev kuralının tek meşru istisnası | H20: UQ1
A21: CurrentStatus | B21: nvarchar(25) | C21: No | D21: DEFAULT ('GENERATED') | G21: Son olaydan TÜRETİLİR (MessageEvent)
A22: GeneratedDate | B22: datetime | C22: Yes
A23: SentDate | B23: datetime | C23: Yes
A24: RawMessageRef | B24: nvarchar(250) | C24: Yes | G24: Güvenli payload deposu referansı — payload DB'de tutulmaz
A25: RawMessageHash | B25: nvarchar(128) | C25: Yes | G25: Bütünlük kontrolü
A26: RetryCount | B26: int | C26: No | D26: DEFAULT (0) | E26: DF_TxnCollateralMessage_RetryCount | G26: Teknik yeniden deneme — yeni talimat DEĞİL
A27: IdempotencyKey | B27: nvarchar(160) | C27: No | E27: UQ2 · UQ_TxnCollateralMessage_IdempotencyKey | G27: 🔴 TxnId + EconomicVersion + MessagePurpose bileşimi | H27: UQ2

Sheet TxnCollateralMessageEvent
A1: TxnCollateralMessageEvent | B1: (doküman adı: collateral_message_event)
A2: Kanal sonuçlarının append-only olay kaydı. 🔑 Accepted ile Settled AYNI ŞEY DEĞİL — her biri ayrı olaydır.
A4: DB NESNELERİ: | B4: ❌ History yok (zaten append-only) · Id: bigint IDENTITY
A6: Kolon Adı | B6: Tip | C6: Null | D6: Default | E6: Index / Constraint | F6: FK Hedefi (FK → PK) | G6: Açıklama | H6: Anahtar / Açık Eşleşme
A7: Id | B7: bigint | C7: No | D7: IDENTITY(1,1) | E7: PK_TxnCollateralMessageEvent | H7: PK
A8: MessageId | B8: bigint | C8: No | E8: IX_TxnCollateralMessageEvent_MessageId_Occurred | F8: TxnCollateralMessage.Id | H8: FK → TxnCollateralMessage.Id (PK)
A9: EventType | B9: nvarchar(30) | C9: No | G9: GENERATED / SENT / ACCEPTED / SETTLED / REJECTED / FAILED
A10: ChannelStatus | B10: nvarchar(60) | C10: Yes | G10: Kanalın ham/normalize durum kodu
A11: OccurredDate | B11: datetime | C11: No | D11: DEFAULT (getdate()) | E11: (IX ile)
A12: ExternalReference | B12: nvarchar(100) | C12: Yes | G12: Ağ/banka/CSD referansı
A13: ErrorCode | B13: nvarchar(60) | C13: Yes
A14: ErrorText | B14: nvarchar(MAX) | C14: Yes | G14: Maskelenmiş hata açıklaması
A15: PayloadHash | B15: nvarchar(128) | C15: Yes
A16: CorrelationId | B16: nvarchar(80) | C16: Yes | G16: Uçtan uca izleme

Sheet CollateralAuditLog
A1: CollateralAuditLog | B1: (doküman adı: collateral_audit_log)
A2: Tüm aggregate'lerin kim/ne zaman/hangi değer değişikliği — append-only.
A4: DB NESNELERİ: | B4: ❌ History yok (zaten log) · Id: bigint IDENTITY · ⚠️ MM'de polymorphic audit tablosu EMSALİ YOK — MM tablo başına <Tablo>History + trigger kullanıyor. Bu tablo History'nin YERİNE değil YANINA konumlanır: History = satır görüntüsü, AuditLog = olay + korelasyon.
A6: Kolon Adı | B6: Tip | C6: Null | D6: Default | E6: Index / Constraint | F6: FK Hedefi (FK → PK) | G6: Açıklama | H6: Anahtar / Açık Eşleşme
A7: Id | B7: bigint | C7: No | D7: IDENTITY(1,1) | E7: PK_CollateralAuditLog | H7: PK
A8: AggregateType | B8: nvarchar(40) | C8: No | E8: IX_CollateralAuditLog_Aggregate | G8: ANNEX / DEFINITION / TRANSACTION / MESSAGE
A9: AggregateId | B9: bigint | C9: No | E9: (IX ile) | F9: ❌ polymorphic — FK yazılamaz | G9: İlgili kaydın Id'si | H9: POLY → ❌ polymorphic — FK yazılamaz
A10: EventType | B10: nvarchar(40) | C10: No | G10: CREATE / UPDATE / VERIFY / SEND / SETTLE / REVERSE
A11: ActorUser | B11: nvarchar(80) | C11: Yes | G11: Kullanıcı veya service account
A12: OccurredDate | B12: datetime | C12: No | D12: DEFAULT (getdate()) | G12: UTC olay zamanı
A13: BeforeData | B13: nvarchar(MAX) | C13: Yes | G13: Değişiklik öncesi JSON (SQL Server'da jsonb yok)
A14: AfterData | B14: nvarchar(MAX) | C14: Yes | G14: Değişiklik sonrası JSON
A15: CorrelationId | B15: nvarchar(80) | C15: Yes | E15: IX_CollateralAuditLog_CorrelationId | G15: İşlem-mesaj uçtan uca izleme
A16: SourceIp | B16: nvarchar(64) | C16: Yes | G16: Maskelenir
A17: Channel | B17: nvarchar(30) | C17: Yes | G17: UI / API / BATCH / ADAPTER

Sheet TxnCollateralPosition
A1: TxnCollateralPosition | B1: (doküman adı: collateral_position)
A2: 🔴 Bakiye projeksiyonu. Dokümanda yalnız kavramsal anılıyor ve kolonları verilmemiş — aşağıdaki kolonlar ÇIKARIMDIR. Zorunlu olma gerekçesi: AC-38 (eşzamanlı iki Decrease) ve AC-09 (bakiye aşımı) yalnız kilitlenebilir bir bakiye satırıyla deterministik olarak önlenebilir; ledger'dan her seferinde SUM almak hem yavaş hem yarış koşuluna açık. Kaynak gerçek DEĞİL — ledger'dan yeniden üretilebilir olmalı.
A4: DB NESNELERİ: | B4: 🔴 v3'te OPSİYONEL DEĞİL ZORUNLU oldu · ❌ History yok · Composite PK (Id kolonu YOK) · Verify ile aynı transaction'da WITH (UPDLOCK, ROWLOCK) güncellenir
A6: Kolon Adı | B6: Tip | C6: Null | D6: Default | E6: Index / Constraint | F6: FK Hedefi (FK → PK) | G6: Açıklama | H6: Anahtar / Açık Eşleşme
A7: DefinitionId | B7: bigint | C7: No | E7: PK_TxnCollateralPosition | F7: DefCollateral.Id | G7: Composite PK #1 (çıkarım) | H7: PK + FK → DefCollateral.Id (PK)
A8: MarginType | B8: nvarchar(15) | C8: No | E8: (PK ile) | G8: Composite PK #2 — VM/IM/IA/OTHER ayrı bakiyeler (doküman §7.3) | H8: PK
A9: AssetCode | B9: nvarchar(12) | C9: No | E9: (PK ile) | G9: Composite PK #3 — Cash: CurrencyCode · Security: ISIN | H9: PK
A10: CollateralType | B10: nvarchar(12) | C10: No | G10: CASH / SECURITY — AssetCode'un hangisi olduğunu söyler
A11: CurrentBalance | B11: decimal(38,10) | C11: No | D11: DEFAULT (0) | G11: Verified/Settled hareketlerden türeyen güncel bakiye
A12: LastTxnId | B12: bigint | C12: Yes | F12: TxnCollateral.Id | G12: Bakiyeyi en son değiştiren işlem — yeniden üretim kontrolü | H12: FK → TxnCollateral.Id (PK)
A13: AsOfDate | B13: datetime | C13: No | D13: DEFAULT (getdate()) | G13: Son güncelleme zamanı
